[
  {
    "title": "श्री हनुमान चालीसा 🌺🙏| GULSHAN KUMAR | HARIHARAN |🙏🌺",
    "vid_id": "AETFvQonfV8",
    "duration": "9:42",
    "god": "hanuman",
    "artist": "Gulshan Kumar, Hariharan"
  },
  {
    "title": "संकटमोचन हनुमान अष्टक, Sankat Mochan Hanuman Ashtak",
    "vid_id": "HH_a6aRO1TE",
    "duration": "6:15",
    "god": "hanuman",
    "artist": "Hariharan"
  },
  {
    "title": "मन मेरा मंदिर Man Mera Mandir Shiv Meri Puja",
    "vid_id": "S6HFRZmZrTI",
    "duration": "6:26",
    "god": "shiv",
    "artist": "Anuradha Paudwal"
  },
  {
    "title": "ॐ जय जगदीश हरे आरती Om Jai Jagdish Hare Aarti",
    "vid_id": "3ucCEjXS9n8",
    "duration": "5:32",
    "god": "vishnu",
    "artist": "Anuradha Paudwal"
  },
  {
    "title": "Gayatri Mantra 108 times",
    "vid_id": "nwRoHC83wx0",
    "duration": "25:18",
    "god": "gayatri",
    "artist": "Anuradha Paudwal"
  },
  {
    "title": "कबीर अमृतवाणी, संत कबीर के Popular Dohe,Kabir Amritwani",
    "vid_id": "HH1PXnKg2LU",
    "duration": "10:20",
    "god": "special, prathna",
    "artist": "Debashish Das Gupta"
  },
  {
    "title": "बजरँग बाण, Bajrang Baan",
    "vid_id": "h1lT6cxwsPw",
    "duration": "7:46",
    "god": "hanuman",
    "artist": "Hariharan"
  },
  {
    "title": "सोमवार Special शिव भजन ऐसी सुबह ना आए",
    "vid_id": "Puyz_7NPl-w",
    "duration": "5:34",
    "god": "shiv",
    "artist": "Anuradha Paudwal"
  },
  {
    "title": "Aarti Ambe Tu Hai Jagdambe Kali",
    "vid_id": "dVTUUtOHUCA",
    "duration": "4:47",
    "god": "durga",
    "artist": "Anuradha Paudwal"
  },
  {
    "title": "छठ पूजा Special उगs हे सूरज देव Uga Hai Suraj Dev",
    "vid_id": "6e6Hp6R5SVU",
    "duration": "5:53",
    "god": "surya",
    "artist": "Anuradha Paudwal"
  },
  {
    "title": "Ganesh Aarti, JAI GANESH DEVA",
    "vid_id": "Yuex2EnsGiY",
    "duration": "4:37",
    "god": "ganesh",
    "artist": "Anuradha Paudwal"
  },
  {
    "title": "Om Jai Shiv Omkara | Lord Shiva Aarti",
    "vid_id": "BhwOproElxU",
    "duration": "4:58",
    "god": "shiv",
    "artist": "Anuradha Paudwal"
  },
  {
    "title": "Aarti Kunj Bihari Ki KRISHNA AARTI",
    "vid_id": "EMO1AT1UQf0",
    "duration": "4:24",
    "god": "krishna",
    "artist": "Hariharan"
  },
  {
    "title": "Hanuman Chalisa - Lyrical Video",
    "vid_id": "17ZHT4WbSfw",
    "duration": "9:49",
    "god": "hanuman",
    "artist": "Gulshan Kumar, Hariharan"
  },
  {
    "title": "Shivji Satya Hai Shiv Bhajan",
    "vid_id": "4-87-bhiSXk",
    "duration": "8:09",
    "god": "shiv",
    "artist": "T-Series"
  },
  {
    "title": "Shiv Shankar Ko Jisne Pooja",
    "vid_id": "w7HbgKcQS_w",
    "duration": "5:35",
    "god": "shiv",
    "artist": "Anuradha Paudwal"
  },
  {
    "title": "Durga Chalisa with Lyrics",
    "vid_id": "AXvmt88JLWg",
    "duration": "8:24",
    "god": "durga",
    "artist": "Anuradha Paudwal"
  },
  {
    "title": "Ajab Hai Teri Maya",
    "vid_id": "ymxaEvSRbho",
    "duration": "6:42",
    "god": "shiv",
    "artist": "Sukhwinder Singh"
  },
  {
    "title": "आरती कीजै हनुमान लला की,hanuman Aarti",
    "vid_id": "r7GJ8GoGSD8",
    "duration": "4:51",
    "god": "hanuman",
    "artist": "Hariharan"
  },
  {
    "title": "हनुमान जी का भजन, संकट हरने वाले को हनुमान ",
    "vid_id": "bpluBKa3QIw",
    "duration": "6:46",
    "god": "hanuman",
    "artist": "Lakhbir Singh Lakkha"
  },
  {
    "title": "प्यारा सजा है तेरा द्वार भवानी ",
    "vid_id": "1pw6VMkH4MA",
    "duration": "6:40",
    "god": "durga",
    "artist": "Lakhbir Singh Lakkha"
  },
  {
    "title": "लेके पूजा की Leke Pooja Ki Thali",
    "vid_id": "Isyq2apnaOk",
    "duration": "5:19",
    "god": "devi",
    "artist": "Suresh Wadkar"
  },
  {
    "title": "तुझे कबसे पुकारे तेरा लाल | Tujhe Kab Se Pukare Tera Laal",
    "vid_id": "ObEt7q0VpvA",
    "duration": "5:29",
    "god": "durga",
    "artist": "Sonu Nigam"
  },
  {
    "title": "Aa Maa Aa Tujhe Dil Ne Pukara - Lyrical Video",
    "vid_id": "IDl-6_LvNgc",
    "duration": "7:33",
    "god": "durga",
    "artist": "Gulshan Kumar"
  },
  {
    "title": "हे शम्भू बाबा Hey Shambhu Baba Mere Bhole Naath",
    "vid_id": "v1QyzO1n0Gg",
    "duration": "5:32",
    "god": "shiv",
    "artist": "Anuradha Paudwal"
  },
  {
    "title": "Khush Honge Hanuman Ram Ram Kiye Jaa",
    "vid_id": "WOEhBViKLNE",
    "duration": "6:04",
    "god": "hanuman",
    "artist": "Lakhbir Singh Lakkha"
  },
  {
    "title": "Ashutosh Shashank Shekhar | आशुतोष शशांक शेखर",
    "vid_id": "toSqahDnlCU",
    "duration": "6:00",
    "god": "shiv",
    "artist": "Sonu Nigam"
  },
  {
    "title": "शिव चालीसा, Shiv Chalisa - Lyrical Video",
    "vid_id": "05g9Ua_M1xA",
    "duration": "14:15",
    "god": "shiv",
    "artist": "Ashwani Amarnath"
  },
  {
    "title": "श्री राम रक्षा स्तोत्र Shree Ram Raksha Stotra",
    "vid_id": "-_axSlApc98",
    "duration": "17:34",
    "god": "ram",
    "artist": "Anuradha Paudwal"
  },
  {
    "title": "Subah Subah Tu Nis Din सुबह सुबह तू निस दिन",
    "vid_id": "wG30okXqs3w",
    "duration": "7:22",
    "god": "shiv",
    "artist": "Anuradha Paudwal"
  },
  {
    "title": "ओ आए तेरे भवन , O Aaye Tere Bhawan",
    "vid_id": "JkXXph945vU",
    "duration": "5:24",
    "god": "devi",
    "artist": "Sonu Nigam, Anuradha Paudwal"
  },
  {
    "title": "Jitna Radha Roee | जितना राधा रोई - Krishna Bhajan",
    "vid_id": "PqkhbFCiJVs",
    "duration": "7:34",
    "god": "krishna",
    "artist": "Saurabh Madhukar"
  },
  {
    "title": "Tera Bhawan Saja Jin Phoolon Se | Bada Sundar Hai Maa Ka Bhawan",
    "vid_id": "QYgvG9zSBfE",
    "duration": "6:21",
    "god": "durga",
    "artist": "Lakhbir Singh Lakkha"
  },
  {
    "title": "Aa Maa Aa Tujhe Dil Ne Pukara",
    "vid_id": "TIrrzcyfFqI",
    "duration": "6:54",
    "god": "durga",
    "artist": "Gulshan Kumar, Babla Mehta"
  },
  {
    "title": "महामृत्युंजय मंत्र  Mahamrityunjay Mantra",
    "vid_id": "A1kqF8NGkPM",
    "duration": "14:56",
    "god": "shiv",
    "artist": "Hemant Chauhan"
  },
  {
    "title": "Dena Hai To De De Sanware",
    "vid_id": "6I2wzS2Bues",
    "duration": "6:34",
    "god": "Khatu Shyam",
    "artist": "Pt. Ram Avtar Sharma"
  },
  {
    "title": "Hey Bhole Shankar Padhaaro हे भोले शंकर पधारो",
    "vid_id": "0pA10Fdr7yM",
    "duration": "6:28",
    "god": "shiv",
    "artist": "Hariharan, Gulshan Kumar"
  },
  {
    "title": "इतना तो कर्ण स्वामी जब प्राण तन से निकले, Itna to Karna Swami Jab Pran Tan Se Nikle",
    "vid_id": "cfMN74Ry0QU",
    "duration": "10:18",
    "god": "prathna",
    "artist": "Anuradha Paudwal"
  },
  {
    "title": "O Aaye Tere Bhawan",
    "vid_id": "l_vU6xIh9f8",
    "duration": "5:15",
    "god": "devi",
    "artist": "Anuradha Paudwal, Sonu Nigam"
  },
  {
    "title": "श्री राम चंद्र कृपालु भजमन Shri Ram Chandra Kripalu",
    "vid_id": "igJHuojQHeo",
    "duration": "6:07",
    "god": "ram",
    "artist": "Suresh Wadkar"
  },
  {
    "title": "श्याम चूड़ी बेचने आया Shyam Choodi, Chudi Bechne Aaya,",
    "vid_id": "UBQHgoCKEc8",
    "duration": "6:32",
    "god": "krishna",
    "artist": "Tripti Shakya"
  },
  {
    "title": "Bigdi Meri Bana De Devi Bhajan",
    "vid_id": "macdUAgZTpY",
    "duration": "6:52",
    "god": "durga",
    "artist": "Lakhbir Singh Lakkha"
  },
  {
    "title": "Shiv Dhun Om Namah Shivay",
    "vid_id": "3FcBh45t9Vs",
    "duration": "47:29",
    "god": "shiv",
    "artist": "Anuradha Paudwal"
  },
  {
    "title": "ऐसी सुबह ना आये | Aisi Subah Na Aaye",
    "vid_id": "p3Z9QmHvpO4",
    "duration": "7:03",
    "god": "shiv",
    "artist": "Madhusmita"
  },
  {
    "title": "मंगलमूर्ति मारुति नंदन | Mangalmurti Maruti Nandan",
    "vid_id": "7NW9j0TgCx8",
    "duration": "6:41",
    "god": "hanuman",
    "artist": "Hariharan"
  },
  {
    "title": "कभी राम बनके कभी श्याम बनके Kabhi Ram Banke Kabhi Shyam Banke",
    "vid_id": "AufHSOus2IM",
    "duration": "8:25",
    "god": "krishna",
    "artist": "Tripti Shakya"
  },
  {
    "title": "जय अम्बे गौरी Jai Ambe Gauri Aarti",
    "vid_id": "3o4eQugO7zk",
    "duration": "9:35",
    "god": "ambe",
    "artist": "Lakhbir Singh Lakkha"
  },
  {
    "title": "Hanuman Tumhara Kya Kehna,हनुमान तुम्हारा क्या कहना ",
    "vid_id": "pbCpkVlwQig",
    "duration": "8:38",
    "god": "hanuman",
    "artist": "Lakhbir Singh Lakkha"
  },
  {
    "title": "Ram Na Milenge Hanuman Ke Bina राम ना मिलेंगे हनुमान के बिना",
    "vid_id": "fdD4_lexi7s",
    "duration": "6:36",
    "god": "hanuman",
    "artist": "Lakhbir Singh Lakkha"
  },
  {
    "title": "Aasman Ko Chukar Dekha | Return Of Hanuman",
    "vid_id": "uHz2ng84hFE",
    "duration": "4:23",
    "god": "hanuman",
    "artist": "Unknown"
  },
  {
    "title": "कभी राम बनके कभी श्याम बनके |Kabhi Ram Banke",
    "vid_id": "mZjySBOJj10",
    "duration": "8:14",
    "god": "krishna",
    "artist": "Tripti Shakya"
  },
  {
    "title": "मेरी झोली छोटी पड़ गई| Meri Jholi Chhoti Pad Gai Re",
    "vid_id": "snMrG8Z0PkY",
    "duration": "7:01",
    "god": "durga",
    "artist": "Narendra Chanchal"
  },
  {
    "title": "बजरंग बाण Bajrang Baan",
    "vid_id": "0DvM8l55GVw",
    "duration": "9:16",
    "god": "hanuman",
    "artist": "Lata Mangeshkar"
  },
  {
    "title": "Ganesh Atharvashirsha गणेश अथर्वशीर्ष",
    "vid_id": "VpATv_6pCPE",
    "duration": "13:21",
    "god": "ganesh",
    "artist": "Anuradha Paudwal"
  },
  {
    "title": "Wo Hai Jag Se Bemisaal|वो है जग से बेमिसाल",
    "vid_id": "P9mGx7iMNM4",
    "duration": "7:51",
    "god": "durga",
    "artist": "Lakhbir Singh Lakkha"
  },
  {
    "title": "Teri Jai Ho Ganesh | तेरी जय हो गणेश",
    "vid_id": "3D6gLI7pFG8",
    "duration": "6:35",
    "god": "ganesh",
    "artist": "Saleem"
  },
  {
    "title": "Hey Shiv Pita Parmatma| हे शिव पिता परमात्मा",
    "vid_id": "i2xv70THcDk",
    "duration": "6:01",
    "god": "shiv",
    "artist": "Hariharan"
  },
  {
    "title": "Milta Hai Sachcha Sukh, मिलता है सच्चा सुख",
    "vid_id": "xwH6LgBIesg",
    "duration": "4:32",
    "god": "shiv",
    "artist": "Anuradha Paudwal"
  },
  {
    "title": "धरती गगन में होती है Dharti Gagan Mein Hoti Hai",
    "vid_id": "cPD8h-Q11u8",
    "duration": "5:28",
    "god": "devi",
    "artist": "Suresh Wadkar, Anuradha Paudwal"
  },
  {
    "title": "केलवा के पात पर , Kelwa Ke Paat Par",
    "vid_id": "knZ8b5YnQiY",
    "duration": "8:35",
    "god": "chhat",
    "artist": "Sharda Sinha"
  },
  {
    "title": "Mahakali Aarti..Mangal Ki Sewa",
    "vid_id": "bVTLWU1QRyE",
    "duration": "7:11",
    "god": "devi",
    "artist": "Anuradha Paudwal"
  },
  {
    "title": "हनुमान चालीसा Hanuman Chalisa",
    "vid_id": "jjbyGOC-mek",
    "duration": "12:13",
    "god": "hanuman",
    "artist": "Mahendra Kapoor"
  },
  {
    "title": "राधे राधे बोल Radhe Radhe Bol",
    "vid_id": "mZPSHAKR_9c",
    "duration": "46:28",
    "god": "radha",
    "artist": "Devi Chitralekha"
  },
  {
    "title": "Om Namah Shivay Dhun 108",
    "vid_id": "ahyW7HFs7rc",
    "duration": "6:27",
    "god": "shiv",
    "artist": "Anuradha Paudwal"
  },
  {
    "title": "मेरी आँखों के सामने ही रहना ",
    "vid_id": "6bQWPmWepeI",
    "duration": "7:41",
    "god": "durga",
    "artist": "Lakhbir Singh Lakkha"
  },
  {
    "title": "O Aaye Tere Bhawan",
    "vid_id": "eLJoiwfyhZk",
    "duration": "4:50",
    "god": "devi",
    "artist": "Sonu Nigam, Anuradha Paudwal"
  },
  {
    "title": "Ho Deenanath|Chhathi Maiya",
    "vid_id": "KWvgJvM2zT0",
    "duration": "6:54",
    "god": "chhat",
    "artist": "Sharda Sinha"
  },
  {
    "title": "प्यारा सजा है तेरा द्वार Pyara Saja Hai Tera Dwar Bhawani",
    "vid_id": "XNL-F02ts2U",
    "duration": "46:41",
    "god": "durga",
    "artist": "Lakhbir Singh Lakkha"
  },
  {
    "title": "ॐ जय जगदीश हरे आरती|Om Jai Jagdish Hare Aarti",
    "vid_id": "-2-gMCFgVC8",
    "duration": "6:50",
    "god": "vishnu",
    "artist": "Lakhbir Singh Lakkha"
  },
  {
    "title": "Hey Shambhu Baba Mere Bhole Nath",
    "vid_id": "i6rDYxNpubk",
    "duration": "3:51",
    "god": "shiv",
    "artist": "Gulshan Kumar"
  },
  {
    "title": "ओ जंगल  के राजा O Jungle Ke Raja",
    "vid_id": "VtiKEC1ziO0",
    "duration": "7:56",
    "god": "ambe",
    "artist": "Anuradha Paudwal"
  },
  {
    "title": "Bheja hai bulawa tune SHERAWALIYE",
    "vid_id": "Xx1Cn67LaEE",
    "duration": "5:27",
    "god": "durga",
    "artist": "Unknown"
  },
  {
    "title": "मेरो मन राम ही रटे Mero Mann Ram Hi Ram Rate Re",
    "vid_id": "Gj0q5ZCy7bE",
    "duration": "5:13",
    "god": "ram",
    "artist": "Anuradha Paudwal"
  },
  {
    "title": "Gokul Ki Galiyon Mein",
    "vid_id": "1N-KBhvJZMk",
    "duration": "3:33",
    "god": "krishna",
    "artist": "Shravan Suresh"
  },
  {
    "title": "Keejo Kesari Ke Laal Hanuman",
    "vid_id": "0zG8JMSqVXs",
    "duration": "6:10",
    "god": "hanuman",
    "artist": "Lakhbir Singh Lakkha"
  },
  {
    "title": "अति सुन्दर प्रार्थना इतनी शक्ति हमें देना दाता Itni Shakti Hamein Dena Data",
    "vid_id": "3EnLaJKhO2A",
    "duration": "4:54",
    "god": "special, prathna",
    "artist": "Anuradha Paudwal"
  },
  {
    "title": "Ek Bar Maa Aajao|Chalo Maa Ke Bhawan Pe",
    "vid_id": "kt7lfJaAxkY",
    "duration": "7:15",
    "god": "durga",
    "artist": "Ram Avtar Sharma"
  },
  {
    "title": "Shyama Aan Baso Vrindavan Mein",
    "vid_id": "XtTG7iT7H3g",
    "duration": "7:37",
    "god": "krishna",
    "artist": "Tripti Shakya"
  },
  {
    "title": "Kelwa ke Paat par |Chhathi Maiya",
    "vid_id": "WsvuH5QO23I",
    "duration": "8:47",
    "god": "chhat",
    "artist": "Devi"
  },
  {
    "title": "Shyam Choodi, Chudi Bechne Aaya",
    "vid_id": "RzVnrYx1qEs",
    "duration": "6:19",
    "god": "krishna",
    "artist": "Tripti Shakya"
  },
  {
    "title": "संकटमोचन हनुमान अष्टक|Sankatmochan Hanuman Ashtak",
    "vid_id": "5hKao7gACW4",
    "duration": "6:19",
    "god": "hanuman",
    "artist": "Hariharan"
  },
  {
    "title": "Leke Pooja Ki Thali Devi Bhajan",
    "vid_id": "W7_C58BskdM",
    "duration": "4:59",
    "god": "durga",
    "artist": "Suresh Wadkar"
  },
  {
    "title": "Ek Tera Sumiran Hey Ram|Ram Bhajan",
    "vid_id": "976W2UzTlrQ",
    "duration": "6:15",
    "god": "ram",
    "artist": "Dilip Mehta"
  },
  {
    "title": "श्री राम स्तुति|Shree Ramchandra Kripalu Bhajman",
    "vid_id": "3q0mbaZjkak",
    "duration": "4:10",
    "god": "ram",
    "artist": "Narendra Chanchal"
  },
  {
    "title": "महाशिवरात्रि विशेष: ॐ जय शिव ओमकारा Om Jai Shiv Omkara Aarti",
    "vid_id": "ymZMV0KqOtE",
    "duration": "7:01",
    "god": "shiv",
    "artist": "Lakhbir Singh Lakkha"
  },
  {
    "title": "आरती कीजै हनुमान लला की|Aarti Keejei Hanuman Lala Ki",
    "vid_id": "DUNYVi_YOq8",
    "duration": "5:49",
    "god": "hanuman",
    "artist": "Lakhbir Singh Lakkha"
  },
  {
    "title": "शिव चालीसा Shiv Chalisa",
    "vid_id": "p01K4EZ-JCY",
    "duration": "10:03",
    "god": "shiv",
    "artist": "Madhusmita"
  },
  {
    "title": "Mahamrityunjay Mantra 108 Times By Anuradha Paudwal",
    "vid_id": "q1uj3_rW7Uc",
    "duration": "39:01",
    "god": "shiv",
    "artist": "Anuradha Paudwal"
  },
  {
    "title": "शिव शंकर को जिसने पूजा Shiv Shankar Ko Jisne Pooja",
    "vid_id": "oBuwBAt5vU8",
    "duration": "5:59",
    "god": "shiv",
    "artist": "Hariharan"
  },
  {
    "title": "तेरी मूर्ति नहीं बोलती Teri Murti Nahin Boldi Bulaya",
    "vid_id": "4jbz-gKaIO8",
    "duration": "6:52",
    "god": "durga",
    "artist": "Narendra Chanchal"
  },
  {
    "title": "शबरी मगन है राम भजन में Shabri Magan Hai",
    "vid_id": "ItLbM6ysRpI",
    "duration": "6:34",
    "god": "ram",
    "artist": "Tripti Shakya"
  },
  {
    "title": "Saare Gaon Se Doodh Manga Kar",
    "vid_id": "S9Po6ijmtmM",
    "duration": "4:40",
    "god": "shiv",
    "artist": "Unknown"
  },
  {
    "title": "Jai Ho Tumhari Bajrangbali",
    "vid_id": "lFHwCJ0Uq1Q",
    "duration": "6:52",
    "god": "hanuman",
    "artist": "Lakhbir Singh Lakkha"
  },
  {
    "title": "होली गीत Julam Kar Daaryo Holi Geet",
    "vid_id": "gmUPxafCmz8",
    "duration": "6:38",
    "god": "krishna",
    "artist": "Lakhbir Singh Lakkha"
  },
  {
    "title": "Aarti Kije Hanuman Lala Ki",
    "vid_id": "gbYXo2Xqlmk",
    "duration": "4:09",
    "god": "hanuman",
    "artist": "Hariharan"
  },
  {
    "title": "Hey Shambhu Baba Mere Bhole Nath",
    "vid_id": "hDD-Q3n56zM",
    "duration": "3:51",
    "god": "shiv",
    "artist": "Gulshan Kumar"
  },
  {
    "title": "Shiv Aaradhana Top Shiv Bhajans By Anuradha Paudwal",
    "vid_id": "68rQ1ILZlic",
    "duration": "31:40",
    "god": "shiv",
    "artist": "Anuradha Paudwal"
  },
  {
    "title": "Jai Kali|Devi Bhajan|Ajj Hai Jagrata",
    "vid_id": "Lohs__sWnOU",
    "duration": "5:32",
    "god": "kali",
    "artist": "Saleem"
  },
  {
    "title": "आते हैं हर साल नौराते माता के Aate Hain Har Saal Naurate Mata Ke",
    "vid_id": "-b_SgBpA0Ok",
    "duration": "7:30",
    "god": "durga",
    "artist": "Lakhbir Singh Lakkha"
  },
  {
    "title": "Surya Chalisa",
    "vid_id": "L8gGSPzxXQU",
    "duration": "9:23",
    "god": "surya",
    "artist": "Anuradha Paudwal"
  },
  {
    "title": "Jagdaati Pahadonwali Maa",
    "vid_id": "XJXEWW5m4c4",
    "duration": "6:23",
    "god": "durga",
    "artist": "Sonu Nigam"
  },
  {
    "title": "Jai Ambe Gauri..Durga Aarti",
    "vid_id": "ncBX5k8wziA",
    "duration": "7:59",
    "god": "durga",
    "artist": "Anuradha Paudwal"
  },
  {
    "title": "108 Names of Durga",
    "vid_id": "dfJpxWb2VVE",
    "duration": "11:31",
    "god": "durga",
    "artist": "Anuradha Paudwal"
  },
  {
    "title": "Tere Dar Pe Sar Jhukaya",
    "vid_id": "DVQY1K7nQFg",
    "duration": "6:05",
    "god": "durga",
    "artist": "Lakhbir Singh Lakkha"
  },
  {
    "title": "Hanuman Jab Chale",
    "vid_id": "3GPtm58cK3I",
    "duration": "8:48",
    "god": "hanuman",
    "artist": "Lakhbir Singh Lakkha"
  },
  {
    "title": "खुश होंगे हनुमान राम राम किये जा Khush Honge Hanuman Ram Ram Kiye Jaa",
    "vid_id": "ANoRlnqRCaU",
    "duration": "6:15",
    "god": "hanuman",
    "artist": "Lakhbir Singh Lakkha"
  },
  {
    "title": "Aana Kailash Ki Choti",
    "vid_id": "zEw_vtqQtf4",
    "duration": "5:25",
    "god": "shiv",
    "artist": "Ram Kumar Lakkha, Lalita"
  },
  {
    "title": "Jai Ambe Gauri Aarti",
    "vid_id": "RY1jmTTjvhI",
    "duration": "7:32",
    "god": "ambe",
    "artist": "Anuradha Paudwal"
  },
  {
    "title": "Sab Mangalmay Kar Dete Hain Dakshin Mukh Ke Hanuman",
    "vid_id": "7qSR2U05Gb8",
    "duration": "7:00",
    "god": "hanuman",
    "artist": "Lakhbir Singh Lakkha"
  },
  {
    "title": "Shri Mahalakshmi Mantra",
    "vid_id": "ORqwmzPfE9M",
    "duration": "11:20",
    "god": "laxmi",
    "artist": "Madhusmita"
  },
  {
    "title": "Maarbo Re Sugva Dhanukh Se| Chhathi Maiya",
    "vid_id": "jRsXRee52xw",
    "duration": "6:43",
    "god": "chhat",
    "artist": "Anuradha Paudwal"
  },
  {
    "title": "महाशिवरात्रि:आओ महिमा गाएं भोलेनाथ की Aao Mahima Gaayen Bholenath Ki",
    "vid_id": "CYQZHxJY-MM",
    "duration": "6:27",
    "god": "shiv",
    "artist": "Anuradha Paudwal"
  },
  {
    "title": "Lakshmi Aarti with Lyrics",
    "vid_id": "SyqgAt-T0iQ",
    "duration": "5:31",
    "god": "laxmi",
    "artist": "Anuradha Paudwal"
  },
  {
    "title": "माँ मुझे दर्शन दे 🙏Mere Nainon Ki Pyaas Bujha De🙏🪔",
    "vid_id": "cLxff7epOb8",
    "duration": "6:17",
    "god": "durga",
    "artist": "Sonu Nigam"
  },
  {
    "title": "Hanuman Ashtak By Hariharan",
    "vid_id": "MeaVRC453M0",
    "duration": "6:04",
    "god": "hanuman",
    "artist": "Hariharan"
  },
  {
    "title": "Hanuman Jab Chale",
    "vid_id": "3GPtm58cK3I",
    "duration": "8:48",
    "god": "hanuman",
    "artist": "Lakhbir Singh Lakkha"
  },
  {
    "title": "कथा राम भक्त हनुमान की Katha Ram Bhakt Hanuman Ki",
    "vid_id": "M1YzJ3cRZpo",
    "duration": "1:52:08",
    "god": "hanuman",
    "artist": "Hariharan"
  },
  {
    "title": "Uga Hai Suraj Dev|Chhath Geet",
    "vid_id": "8MzoVsjL4QU",
    "duration": "6:02",
    "god": "chhat",
    "artist": "Anuradha Paudwal"
  },
  {
    "title": "हे नाथ प्रार्थना Hey Nath Prarthana",
    "vid_id": "Gyce_jb8ZHg",
    "duration": "5:33",
    "god": "shiv",
    "artist": "Ashwani Amarnath"
  },
  {
    "title": "Subah Subah Le Shiv Ka Naam By Gulshan Kumar",
    "vid_id": "TplRlUULXz8",
    "duration": "5:36",
    "god": "shiv",
    "artist": "Gulshan Kumar"
  },
  {
    "title": "Ho Deenanath | BHOJPURI CHHATH GEET",
    "vid_id": "fOVGz9WFymU",
    "duration": "3:47",
    "god": "chhat",
    "artist": "Sharda Sinha"
  },
  {
    "title": "श्री हनुमान चालीसा|Hanuman Chalisa",
    "vid_id": "D8hF5uSP3u8",
    "duration": "11:35",
    "god": "hanuman",
    "artist": "Lata Mangeshkar"
  },
  {
    "title": "Om Gan Ganpataye Namo Namah Anuradha Paudwal",
    "vid_id": "YXRO9M-bQA0",
    "duration": "6:37",
    "god": "ganesh",
    "artist": "Anuradha Paudwal"
  },
  {
    "title": "Meri Ankhiyon Ke Samne Hi Rehna",
    "vid_id": "0diZqEfx6_A",
    "duration": "7:49",
    "god": "durga",
    "artist": "Lakhbir Singh Lakkha"
  },
  {
    "title": "नवरात्रि Special: Maiya Ka Chola Hai",
    "vid_id": "IHyTxAR51Ow",
    "duration": "7:04",
    "god": "durga",
    "artist": "Lakhbir Singh Lakkha"
  },
  {
    "title": "Om Jai Jagdish Hare",
    "vid_id": "77KlDA2QhrA",
    "duration": "10:57",
    "god": "vishnu",
    "artist": "Babita Sharma"
  },
  {
    "title": "Mann Bhabe Maiya Ke Chunariya",
    "vid_id": "fYHaz39UL8M",
    "duration": "4:57",
    "god": "durga",
    "artist": "Anuradha Paudwal"
  },
  {
    "title": "Man Ki Muraden Poori Kar Maa",
    "vid_id": "VXJchr21U3M",
    "duration": "6:55",
    "god": "durga",
    "artist": "Lakhbir Singh Lakkha"
  },
  {
    "title": "Man Leke Aaya Mata Rani Ke Bhawan Mein",
    "vid_id": "UUAJFjov7Xo",
    "duration": "9:10",
    "god": "durga",
    "artist": "Gulshan Kumar"
  },
  {
    "title": "Ganga Nahavan Aai Soon",
    "vid_id": "bjuVhZivxW0",
    "duration": "7:56",
    "god": "shiv",
    "artist": "Anuradha Paudwal"
  },
  {
    "title": "Shendoor Lal Chadhayo",
    "vid_id": "8yv5kMuk31Y",
    "duration": "3:10",
    "god": "ganesh",
    "artist": "Anuradha Paudwal"
  },
  {
    "title": "Om Gan Ganpataye Namo Namah|Ganesh Mantra",
    "vid_id": "2WIvgVxsiAk",
    "duration": "41:30",
    "god": "ganesh",
    "artist": "Kartiki Gaikwad"
  },
  {
    "title": "Shani Amritwani By Anuradha Paudwal [Full Video Song]|Shri Shanidev Amritwani",
    "vid_id": "e3K3BREwxRQ",
    "duration": "19:57",
    "god": "shani",
    "artist": "Anuradha Paudwal"
  },
  {
    "title": "Kelwa Ke Paat Par By Sharda Sinha Bhojpuri Chhath Songs [Full Song] Chhathi Maiya",
    "vid_id": "-mpGoG0nWPo",
    "duration": "8:25",
    "god": "chhat",
    "artist": "Sharda Sinha"
  },
  {
    "title": "KOPI KOPI BOLELI | Chhath Pooja",
    "vid_id": "YVrZBmI9_ag",
    "duration": "6:26",
    "god": "chhat",
    "artist": "Devi"
  },
  {
    "title": "Mangalmurti Maruti Nandan",
    "vid_id": "0cPiC1c6X4E",
    "duration": "6:37",
    "god": "hanuman",
    "artist": "Hariharan"
  },
  {
    "title": "Ho Deenanath|Chhathi Maiya",
    "vid_id": "j74EcjyN1WQ",
    "duration": "6:51",
    "god": "chhat",
    "artist": "Sharda Sinha"
  },
  {
    "title": "Kelwa Ke Paat Par | Chhath Geet",
    "vid_id": "AaDo9XynbuM",
    "duration": "8:25",
    "god": "chhat",
    "artist": "Anuradha Paudwal"
  },
  {
    "title": "Aa Maa Aa Tujhe Dil Ne Pukara",
    "vid_id": "3B96njAMwD4",
    "duration": "6:55",
    "god": "durga",
    "artist": "Gulshan Kumar"
  },
  {
    "title": "Aaja Maa Tenu Ankhiyan Udeek Diyaan",
    "vid_id": "aUVJOjWIhrY",
    "duration": "5:25",
    "god": "devi",
    "artist": "Gulshan Kumar"
  },
  {
    "title": "साईं अमृतवाणी Sai Amritwani",
    "vid_id": "bQwSXJEjQXg",
    "duration": "19:48",
    "god": "sai",
    "artist": "Anuradha Paudwal"
  },
  {
    "title": "Meri Pooja Kar Sweekaar",
    "vid_id": "meNvc_RjXFo",
    "duration": "4:43",
    "god": "kali",
    "artist": "Anuradha Paudwal"
  },
  {
    "title": "Mauj Lag Gayi|Devi Bhajan",
    "vid_id": "b8hNlSJcfXQ",
    "duration": "5:56",
    "god": "durga",
    "artist": "Saleem"
  },
  {
    "title": "Aaja Maa Ek Baar Mere Ghar Aaja",
    "vid_id": "Ksz8fVgGaDM",
    "duration": "5:29",
    "god": "durga",
    "artist": "Anuradha Paudwal"
  },
  {
    "title": "Maiya Ka Chola Hai Rangla",
    "vid_id": "HCLqyZlxFS8",
    "duration": "6:31",
    "god": "durga",
    "artist": "Lakhbir Singh Lakkha"
  },
  {
    "title": "Bhola Ke Dhaam Chala | Shiv Bhajan",
    "vid_id": "hBOZrxVwiGw",
    "duration": "5:53",
    "god": "shiv",
    "artist": "Anuradha Paudwal"
  },
  {
    "title": "Subah Subah Le Shiv Ka Naam By Gulshan Kumar,Hariharan",
    "vid_id": "0NNmFkQ0GeE",
    "duration": "6:13",
    "god": "shiv",
    "artist": "Gulshan Kumar, Hariharan"
  },
  {
    "title": "Chal Kanwariya Chal Kanwariya",
    "vid_id": "8QTh6-vcbz8",
    "duration": "5:36",
    "god": "shiv",
    "artist": "Gulshan Kumar"
  },
  {
    "title": "शबरी मगन है राम भजन में Shabri Magan Hai Ram Bhajan Mein",
    "vid_id": "5je_bEdSYHA",
    "duration": "6:42",
    "god": "ram",
    "artist": "Tripti Shakya"
  },
  {
    "title": "Sankat Mochan Hanuman Ashtak",
    "vid_id": "1zS2sgVEjvs",
    "duration": "7:02",
    "god": "hanuman",
    "artist": "Hariom Sharan"
  },
  {
    "title": "Ho Dinaanaath",
    "vid_id": "f-WsraDBPnY",
    "duration": "9:01",
    "god": "chhat",
    "artist": "Sharda Sinha"
  },
  {
    "title": "Kab Aayoge Balaji Maharaj",
    "vid_id": "rS00v2T6cK4",
    "duration": "5:33",
    "god": "hanuman",
    "artist": "Ram Avtar Sharma"
  },
  {
    "title": "Main Pardesi Hoon",
    "vid_id": "9YTQkmcbnAM",
    "duration": "8:29",
    "god": "durga",
    "artist": "Anuradha Paudwal"
  },
  {
    "title": "Shiv Aaradhana",
    "vid_id": "68rQ1ILZlic",
    "duration": "31:40",
    "god": "shiv",
    "artist": "Anuradha Paudwal"
  },
  {
    "title": "Ganesh Vandana",
    "vid_id": "kE_3b_NaOAE",
    "duration": "4:18",
    "god": "ganesh",
    "artist": "Saleem"
  },
  {
    "title": "Hey Krishna",
    "vid_id": "ZY3hckZx0yQ",
    "duration": "2:05",
    "god": "krishna",
    "artist": "Sonu Nigam"
  },
  {
    "title": "Jai Saraswati Mata",
    "vid_id": "TTVAyS9wOV4",
    "duration": "5:00",
    "god": "saraswati",
    "artist": "Anuradha Paudwal"
  },
  {
    "title": "Koi Nahin Pardes Mein Mera",
    "vid_id": "oqjRSnWwHQc",
    "duration": "6:57",
    "god": "durga",
    "artist": "Sonu Nigam"
  },
  {
    "title": "गणेश चालीसा Ganesh Chalisa",
    "vid_id": "WyHFSjN0miU",
    "duration": "9:08",
    "god": "ganesh",
    "artist": "Anuradha Paudwal"
  },
  {
    "title": "Main Hoon Daasi Teri Daatiye",
    "vid_id": "Wmi4xIRGysU",
    "duration": "4:12",
    "god": "devi",
    "artist": "Anuradha Paudwal"
  },
  {
    "title": "Main Balak Tu Mata Sheranwaliye",
    "vid_id": "fjfCXQKbqdE",
    "duration": "6:02",
    "god": "durga",
    "artist": "Gulshan Kumar"
  },
  {
    "title": "Bum Bhole Bum Bhole",
    "vid_id": "mUsDy0LQYDM",
    "duration": "7:27",
    "god": "shiv",
    "artist": "Satpal Rohatiya"
  },
  {
    "title": "Shankar Mera Pyara",
    "vid_id": "nlQ0INL8V60",
    "duration": "6:39",
    "god": "shiv",
    "artist": "Anuradha Paudwal"
  },
  {
    "title": "ओ आये तेरे भवन O Aaye Tere Bhawan",
    "vid_id": "-P_tNWJRcVM",
    "duration": "5:05",
    "god": "durga",
    "artist": "Anuradha Paudwal, Sonu Nigam"
  },
  {
    "title": "Jai Jai Jai Hanuman Gusai",
    "vid_id": "NIkONVRvJzM",
    "duration": "4:17",
    "god": "hanuman",
    "artist": "Hariharan"
  },
  {
    "title": "एक भक्त की माँ से प्रार्थना Jagdaati Pahadonwali Maa",
    "vid_id": "UEJ19287lxQ",
    "duration": "6:34",
    "god": "durga",
    "artist": "Sonu Nigam"
  },
  {
    "title": "Charno Mein Rakhna",
    "vid_id": "_nPKpP8HC0w",
    "duration": "6:36",
    "god": "durga",
    "artist": "Anuradha Paudwal"
  },
  {
    "title": "Suno Suno Saanware Ki",
    "vid_id": "Iy2QTcd-_is",
    "duration": "2:54",
    "god": "krishna",
    "artist": "Shreya Ghoshal"
  },
  {
    "title": "Jode Jode Supwa | Chhathi Maiya",
    "vid_id": "G3PMFpftpbg",
    "duration": "5:15",
    "god": "chhat",
    "artist": "Kalpana"
  },
  {
    "title": "Hanuman Jayanti Bhajans",
    "vid_id": "ASb9b3pHglU",
    "duration": "57:46",
    "god": "hanuman",
    "artist": "Hariom Sharan, Hariharan, Lata Mangeshkar"
  },
  {
    "title": "आते हैं हर साल नौराते माता के Aate Hain Har Saal Naurate Mata Ke",
    "vid_id": "-b_SgBpA0Ok",
    "duration": "7:30",
    "god": "durga",
    "artist": "Lakhbir Singh Lakkha"
  },
  {
    "title": "Surya Chalisa with Hindi English Lyrics",
    "vid_id": "L8gGSPzxXQU",
    "duration": "9:23",
    "god": "surya",
    "artist": "Anuradha Paudwal"
  },
  {
    "title": "Jagdaati Pahadonwali Maa",
    "vid_id": "XJXEWW5m4c4",
    "duration": "6:23",
    "god": "durga",
    "artist": "Sonu Nigam"
  },
  {
    "title": "Mehranwaliye Maaye Boohe Mandiran De Khol",
    "vid_id": "NfOOP27ECTQ",
    "duration": "7:56",
    "god": "durga",
    "artist": "Unknown"
  },
  {
    "title": "तेरी आँखों के तारे करोड़ों माँ Teri Aankhon Ke Taare Karodon Maa",
    "vid_id": "iLol3P4cFI0",
    "duration": "6:44",
    "god": "durga",
    "artist": "Narendra Chanchal"
  },
  {
    "title": "Dil Wali Palki Wich Tenu",
    "vid_id": "IoF9xiRF5nQ",
    "duration": "7:25",
    "god": "durga",
    "artist": "Unknown"
  },
  {
    "title": "Ganesh Amritdhara",
    "vid_id": "hwfll6dBgMg",
    "duration": "44:41",
    "god": "ganesh",
    "artist": "Debashish Das Gupta"
  },
  {
    "title": " Mere Ghar Aao Lakshmi Maa",
    "vid_id": "LbrI3NOE6Lk",
    "duration": "46:01",
    "god": "laxmi",
    "artist": "Anuradha Paudwal"
  },
  {
    "title": "Hari Om Namah Shivay",
    "vid_id": "-Y7TsJx4B7o",
    "duration": "22:03",
    "god": "shiv",
    "artist": "Prakash Panrekar"
  },
  {
    "title": "सोमवार Special Non Stop शिवजी के भजन",
    "vid_id": "EJPVjtU2X40",
    "duration": "45:29",
    "god": "shiv",
    "artist": "Anuradha Paudwal, Suresh Wadkar"
  },
  {
    "title": "ॐ ऐं ह्रीं क्लीं Om Aim Hrim Klim",
    "vid_id": "RsvKnNzqWsk",
    "duration": "19:23",
    "god": "durga",
    "artist": "Anuradha Paudwal"
  },
  {
    "title": "Om Jai Lakshmi Mata Aarti",
    "vid_id": "5ttUSe1Jp-Q",
    "duration": "7:23",
    "god": "laxmi",
    "artist": "Anuradha Paudwal"
  },
  {
    "title": "Karpur Gauram Karunavtaram",
    "vid_id": "9x7YKVEADLY",
    "duration": "5:20",
    "god": "durga",
    "artist": "Pawan Singh"
  },
  {
    "title": "Patna Ke Ghatva Par | Chhath Geet",
    "vid_id": "VkYrntXiEX8",
    "duration": "4:47",
    "god": "chhat",
    "artist": "T-Series"
  },
  {
    "title": "Uthau Suruj Bhaile Bihaan | Chhathi Maiya",
    "vid_id": "j9G3caThH98",
    "duration": "5:19",
    "god": "chhat",
    "artist": "Sharda Sinha"
  },
  {
    "title": "Om Namah Shivay Dhun ॐ नमः शिवाय धुन ",
    "vid_id": "SXHZSdRp-dI",
    "duration": "4:44",
    "god": "shiv",
    "artist": "Anuradha Paudwal"
  },
  {
    "title": "Kahanva Tohar Naihara Ge Dhobin|Chhathi Maiya",
    "vid_id": "waKku0zzRyY",
    "duration": "6:19",
    "god": "chhat",
    "artist": "T-Series"
  },
  {
    "title": "भोलेनाथ Bholenath Bhangadhi Teri Bhang",
    "vid_id": "Bk1QgH9E4iQ",
    "duration": "4:25",
    "god": "shiv",
    "artist": "Shah Sister"
  },
  {
    "title": "मंगलवार Special Bajrang Baan|बजरंग बाण",
    "vid_id": "ZMJkjmPEdWc",
    "duration": "7:46",
    "god": "hanuman",
    "artist": "Hariharan"
  },
  {
    "title": "आरती कीजै हनुमान लला की|Aarti Keejei Hanuman Lala Ki",
    "vid_id": "ijxRwMmx8r4",
    "duration": "5:52",
    "god": "hanuman",
    "artist": "Hari Om Sharan"
  },
  {
    "title": "जन्माष्टमी आरती: आरती कुंज बिहारी की, Aarti Kunj Bihari Ki",
    "vid_id": "FEMR5alT7CY",
    "duration": "4:28",
    "god": "krishna",
    "artist": "Anuradha Paudwal"
  },
  {
    "title": "Shri Ram Stuti with Lyrics",
    "vid_id": "3lRt8gUSPB0",
    "duration": "3:44",
    "god": "ram",
    "artist": "Nitin Mukesh"
  },
  {
    "title": "मंगलवार Special - Kaahe Garje",
    "vid_id": "V4Xo2fGkvuY",
    "duration": "6:48",
    "god": "hanuman",
    "artist": "Lakhbir Singh Lakkha"
  },
  {
    "title": "Kauna Munh Shiv Jogi",
    "vid_id": "g4T6anKcUDw",
    "duration": "5:41",
    "god": "shiv",
    "artist": "Sharda Sinha, Vandana"
  },
  {
    "title": "Radhe Radhe Bol",
    "vid_id": "3Umi_0UCnaI",
    "duration": "6:43",
    "god": "radha",
    "artist": "Devi Chitralekha"
  },
  {
    "title": "Rama Rama Ram Ho",
    "vid_id": "cFcioPFV6cU",
    "duration": "3:51",
    "god": "ram",
    "artist": "Tripti Shakya, Uday"
  },
  {
    "title": "काँच ही बाँस के बहंगिया|Kaanch Hi Baans Ke Bahangiya",
    "vid_id": "8dNjbCHaGEc",
    "duration": "4:10",
    "god": "chhat",
    "artist": "Anuradha Paudwal"
  },
  {
    "title": "साँवरा जरूर  आएगा|Sanwara Jaroor Aayega",
    "vid_id": "J5y5Z3SM4Ww",
    "duration": "6:53",
    "god": "Khatu Shyam",
    "artist": "Rajani Rajasthani"
  },
  {
    "title": "Om Aim Hrim Klim Chamundaye Vichche 108 times",
    "vid_id": "cdlS1XC3Gus",
    "duration": "14:33",
    "god": "durga",
    "artist": "Anuradha Paudwal"
  },
  {
    "title": "Jal Beech Khada Hoeeb",
    "vid_id": "Xyan5v136U0",
    "duration": "5:27",
    "god": "chhat",
    "artist": "Pawan Singh"
  },
  {
    "title": "Shiv Shankar Ka Gungaan",
    "vid_id": "jeW8LHnzGn8",
    "duration": "10:04",
    "god": "shiv",
    "artist": "Gulshan Kumar"
  },
  {
    "title": "Ran Mein Kood Gayi Mahakali",
    "vid_id": "CQfPnCYVntY",
    "duration": "6:54",
    "god": "devi",
    "artist": "Narendra Chanchal"
  },
  {
    "title": "Tere Sadke Tu Bhej De Bulava",
    "vid_id": "4he0JAeiBo8",
    "duration": "6:01",
    "god": "durga",
    "artist": "Anuradha Paudwal"
  },
  {
    "title": "Surya Aarti, Om Jai Surya Bhagwan",
    "vid_id": "F9uURnkc8iA",
    "duration": "5:34",
    "god": "surya",
    "artist": "Anuradha Paudwal"
  },
  {
    "title": "Govinda Namam - Sri Venkatesham Manase Smarami",
    "vid_id": "IbGOnKpHWIs",
    "duration": "10:45",
    "god": "venkatesh",
    "artist": "T-Series"
  },
  {
    "title": "रविवार Special चार धाम महिमा Karlo Karlo Charon Dham",
    "vid_id": "9HX3OGujr5c",
    "duration": "7:23",
    "god": "prathna",
    "artist": "Gulshan Kumar"
  },
  {
    "title": "Mahalakshmi Mantra 108 times",
    "vid_id": "2d0IOpaJ7PQ",
    "duration": "26:36",
    "god": "laxmi",
    "artist": "Anuradha Paudwal"
  },
  {
    "title": "Rudrashtakam in Sanskrit",
    "vid_id": "GcWXVSiKoH4",
    "duration": "4:06",
    "god": "shiv",
    "artist": "Anuradha Paudwal"
  },
  {
    "title": "Hey Chhathi Maiya",
    "vid_id": "x9_3sARy_Kw",
    "duration": "4:58",
    "god": "chhat",
    "artist": "Sharda Sinha"
  },
  {
    "title": "Shanaishwara Shanaishwara",
    "vid_id": "7MhfQOgWMyc",
    "duration": "6:59",
    "god": "shani",
    "artist": "Anuradha Paudwal, Hariharan"
  },
  {
    "title": "Maiya Meri Sherawali, Maiya Ka Jawab Nahin",
    "vid_id": "BFyiH3dBrNI",
    "duration": "6:50",
    "god": "durga",
    "artist": "Lakhbir Singh Lakkha"
  },
  {
    "title": "Mehandipur Ke Balaji",
    "vid_id": "dvgMfrtvDH4",
    "duration": "7:15",
    "god": "hanuman",
    "artist": "Narendra Kaushik"
  },
  {
    "title": "Putana (Bachcho Zara Door Door Rahena Re)",
    "vid_id": "BFtBgCFF-Zc",
    "duration": "3:46",
    "god": "krishna",
    "artist": "Shravan Suresh"
  },
  {
    "title": "श्री दुर्गा चालीसा Shree Durga Chalisa",
    "vid_id": "RQTXD23-JLg",
    "duration": "8:28",
    "god": "durga",
    "artist": "Anuradha Paudwal"
  },
  {
    "title": "महादेव शंकर हैं|Mahadev Shankar Hain Jag Se Nirale",
    "vid_id": "hLaKkvO9gok",
    "duration": "4:31",
    "god": "shiv",
    "artist": "Hariharan"
  },
  {
    "title": "Om Gan Ganpataye Namo Namah Ganesh Mantra",
    "vid_id": "pR0zINRgNHc",
    "duration": "36:14",
    "god": "ganesh",
    "artist": "Hemant Chauhan"
  },
  {
    "title": "Baanjhi Kewdwa Dhaile Thaadh|Chhathi Maiya",
    "vid_id": "MEnyozgodAU",
    "duration": "9:01",
    "god": "chhat",
    "artist": "Sharda Sinha"
  },
  {
    "title": "सारे गाँव से दूध मँगाकर Saare Gaon Se Doodh",
    "vid_id": "33dE8wAwBgU",
    "duration": "5:10",
    "god": "shiv",
    "artist": "Anuradha Paudwal"
  },
  {
    "title": "श्री शनिदेव अमृतवाणी Shree Shanidev Amritwani",
    "vid_id": "X_jWC_8HDvI",
    "duration": "4:39",
    "god": "shani",
    "artist": "Anuradha Paudwal"
  },
  {
    "title": "इन आँखों में सूरत|In Ankhon Mein Surat Hai Teri",
    "vid_id": "wDlD5F5XyBo",
    "duration": "6:22",
    "god": "shiv",
    "artist": "Anuradha Paudwal"
  },
  {
    "title": "Shiv Chalisa |Shri Somnath Amritwani",
    "vid_id": "-mUoM-sSzkc",
    "duration": "9:52",
    "god": "shiv",
    "artist": "Gulshan Kumar, Suresh Wadkar"
  },
  {
    "title": "मेरी रक्षा करो बजरंगबली Meri Raksha Karo Bajrangbali",
    "vid_id": "15K93UOQkPE",
    "duration": "5:13",
    "god": "hanuman",
    "artist": "Gulshan Kumar, Babla Mehta"
  },
  {
    "title": "नवरात्रि Special Mann Leke Aaya Mata Rani Bhawan Mein",
    "vid_id": "6VXhDj675EA",
    "duration": "9:20",
    "god": "durga",
    "artist": "Anuradha Paudwal"
  },
  {
    "title": "Shri Ram Jai Ram Jai Jai Ram Keertan",
    "vid_id": "B241lEeK_as",
    "duration": "19:16",
    "god": "ram",
    "artist": "Anuradha Paudwal"
  },
  {
    "title": "Tujhe Note Chahiye Ya Dolar",
    "vid_id": "LEe4UVWebpM",
    "duration": "4:10",
    "god": "shiv",
    "artist": "Ram Kumar Lakkha, Lalita"
  },
  {
    "title": "श्री बाँके बिहारी लाल|Shree Banke Bihari Laal",
    "vid_id": "sLns6FMSVLc",
    "duration": "5:53",
    "god": "krishna",
    "artist": "Lakhbir Singh Lakkha"
  },
  {
    "title": "सब मंगलमय कर देते हैं Sab Mangalmay Kar Dete Hain",
    "vid_id": "S4WfRck4zKQ",
    "duration": "7:01",
    "god": "hanuman",
    "artist": "Lakhbir Singh Lakkha"
  },
  {
    "title": "Blackhole|Return Of Hanuman",
    "vid_id": "eOWQV6XpsFQ",
    "duration": "2:52",
    "god": "hanuman",
    "artist": "T-Series"
  },
  {
    "title": "MELA MAIYA DA",
    "vid_id": "_LeQC4auOAo",
    "duration": "5:09",
    "god": "durga",
    "artist": "Saleem"
  },
  {
    "title": "Mahashivratri Special, Hey Bhole Shankar Padharo",
    "vid_id": "JXAh2MU5dGs",
    "duration": "5:36",
    "god": "shiv",
    "artist": "Hariharan"
  },
  {
    "title": "Jai Santoshi Mata Aarti",
    "vid_id": "LCYAyR6EmDI",
    "duration": "7:57",
    "god": "devi",
    "artist": "Anuradha Paudwal"
  },
  {
    "title": "Mere Naino Ki Pyas Bujha De",
    "vid_id": "8hONQH8CvQA",
    "duration": "6:00",
    "god": "devi",
    "artist": "Sonu Nigam"
  },
  {
    "title": "Amrit Ki Barse Badariya",
    "vid_id": "UC0v41IBGpY",
    "duration": "6:51",
    "god": "durga",
    "artist": "Lakhbir Singh Lakkha"
  },
  {
    "title": "Hey Chhathi Maiya",
    "vid_id": "4B7Epg85nfI",
    "duration": "6:11",
    "god": "chhat",
    "artist": "Sharda Sinha"
  },
  {
    "title": "भोले गिरजापति हूँ तुम्हारी शरण Bhole Girjapati Hoon Tumhari Sharan",
    "vid_id": "9GQ7w9hNxQA",
    "duration": "9:47",
    "god": "shiv",
    "artist": "Lakhbir Singh Lakkha"
  },
  {
    "title": "Shiv Amritwani |Jyotirling Hai Shiv Ki Jyoti",
    "vid_id": "5uAOIJ084g0",
    "duration": "19:49",
    "god": "shiv",
    "artist": "Anuradha Paudwal"
  },
  {
    "title": "मीरा बाई का अति प्राचीन भजन ऐसी लागी लगन|Aisi Laagi Lagan",
    "vid_id": "9iNPMak7UIU",
    "duration": "5:55",
    "god": "krishna",
    "artist": "Anuradha Paudwal"
  },
  {
    "title": "Maiya Ri Maiya [Full Song] Ye Maa Ka Jagrata Hai",
    "vid_id": "3ZA7UKGrUyk",
    "duration": "5:43",
    "god": "durga",
    "artist": "T-Series"
  },
  {
    "title": "सारी दुनिया करे Saari Duniya Kare",
    "vid_id": "sSkGmmBywbY",
    "duration": "6:16",
    "god": "durga",
    "artist": "Lakhbir Singh Lakkha"
  },
  {
    "title": "Shiv Vivah",
    "vid_id": "Ht_3AwYiYjY",
    "duration": "6:30",
    "god": "shiv",
    "artist": "Saleem"
  },
  {
    "title": "108 Names of Lord Shiva शिव जी के १०८ नाम ",
    "vid_id": "fVpspLFibBQ",
    "duration": "7:33",
    "god": "shiv",
    "artist": "Anuradha Paudwal"
  },
  {
    "title": "Jai Ambe Gauri",
    "vid_id": "jsYWCRJq3CY",
    "duration": "5:00",
    "god": "ambe",
    "artist": "T-Series"
  },
  {
    "title": "Ramnavmi 2016|Ram Chalisa",
    "vid_id": "I3Ze7RasX6A",
    "duration": "10:10",
    "god": "ram",
    "artist": "Shekhar Sen"
  },
  {
    "title": "नवरात्रि Special बेटा जो बुलाये माँ को आना चाहिये Beta Jo Bulaye Maa Ko Aana Chahiye",
    "vid_id": "EYa-m7Cq5SA",
    "duration": "7:36",
    "god": "durga",
    "artist": "Gulshan Kumar"
  },
  {
    "title": "Devi Kavach|Navdurga Stuti",
    "vid_id": "Xa4iOtAxRmw",
    "duration": "10:55",
    "god": "durga",
    "artist": "Anuradha Paudwal"
  },
  {
    "title": "Main Deewana Sai Tera",
    "vid_id": "SsWWzYgkZ4s",
    "duration": "6:45",
    "god": "sai",
    "artist": "Lakhbir Singh Lakkha"
  },
  {
    "title": "Maa Ka Dil",
    "vid_id": "qNRYkkI4WCM",
    "duration": "23:57",
    "god": "durga",
    "artist": "Sonu Nigam"
  },
  {
    "title": "Jai Jwala Maa|Jaikara Jotanwali Ka",
    "vid_id": "ELzyA8wGXG8",
    "duration": "5:38",
    "god": "durga",
    "artist": "Gulshan Kumar"
  },
  {
    "title": "Maarbo Re Sugwa| Chhath Geet",
    "vid_id": "OnoINkPrhK0",
    "duration": "6:47",
    "god": "chhat",
    "artist": "Anuradha Paudwal"
  },
  {
    "title": "Shankar Mera Pyara",
    "vid_id": "8RbMUPGhxBI",
    "duration": "3:40",
    "god": "shiv",
    "artist": "Tulsi Kumar, Anuradha Paudwal"
  },
  {
    "title": "Suno Suno Ek Kahani Devi Bhajan",
    "vid_id": "iCoG4zwooUU",
    "duration": "7:03",
    "god": "durga",
    "artist": "Vipin Sachdeva"
  },
  {
    "title": "Khol Deen Kewadiya Ye Baba",
    "vid_id": "f9bHW5_nkvg",
    "duration": "7:01",
    "god": "shiv",
    "artist": "Sunil Chaaila Bihari"
  },
  {
    "title": "Khilona Maati Ka",
    "vid_id": "0qZUzoeSXIU",
    "duration": "7:17",
    "god": "krishna",
    "artist": "Tripti Shakya"
  },
  {
    "title": "Vishwanathashtakam",
    "vid_id": "hEYbVtf0UNQ",
    "duration": "3:50",
    "god": "shiv",
    "artist": "S.P. Balasubrahmaniam"
  },
  {
    "title": "Shiv Shankar Ka Gungaan Karo",
    "vid_id": "ZTCM3fjMFm0",
    "duration": "5:03",
    "god": "shiv",
    "artist": "Gulshan Kumar"
  },
  {
    "title": "Chaar Hi Chakka Ke Motarva | Chhath Pooja Ke Geet",
    "vid_id": "Kxqx7xjLCCo",
    "duration": "4:43",
    "god": "chhat",
    "artist": "T-Series"
  },
  {
    "title": "Ganesh Amritwani",
    "vid_id": "TeTF3J5biAw",
    "duration": "5:24",
    "god": "ganesh",
    "artist": "Anuradha Paudwal"
  },
  {
    "title": "Jo Bhi Aaya Hai Tere Dware",
    "vid_id": "H_WUBVJuON8",
    "duration": "5:20",
    "god": "durga",
    "artist": "Sukhwinder"
  },
  {
    "title": "APNE RANG MEIN RANG LE",
    "vid_id": "gPNd_VegQJQ",
    "duration": "8:37",
    "god": "hanuman",
    "artist": "Narendra Kaushik"
  },
  {
    "title": "Aadit Manaila Bhojpuri Chhath Geet",
    "vid_id": "kEJsJ7wn5Zw",
    "duration": "5:24",
    "god": "chhat",
    "artist": "T-Series"
  },
  {
    "title": "Kankariya Se Matki Phodi",
    "vid_id": "gP96KR7DNCI",
    "duration": "6:07",
    "god": "krishna",
    "artist": "Lakhbir Singh Lakkha"
  },
  {
    "title": "होली गीत Julam Kar Daaryo",
    "vid_id": "0lxIlj6WfTw",
    "duration": "6:40",
    "god": "krishna",
    "artist": "Lakhbir Singh Lakkha"
  },
  {
    "title": "बजरंग बाण, Bajrang Baan",
    "vid_id": "dkp7KfGo0gM",
    "duration": "6:35",
    "god": "hanuman",
    "artist": "Narendra Chanchal"
  },
  {
    "title": "Mahamrityunjay Mantra",
    "vid_id": "hF88XjrSoDk",
    "duration": "6:36",
    "god": "shiv",
    "artist": "Anuradha Paudwal"
  },
  {
    "title": "Tohe Badka Bhaiya Ho By Sharda Sinha Bhojpuri Chhath Songs",
    "vid_id": "O4ARvvmllCA",
    "duration": "5:54",
    "god": "chhat",
    "artist": "Sharda Sinha"
  },
  {
    "title": "Nilanjan Samabhasam Mantra 108 times",
    "vid_id": "YeZYMUJErjA",
    "duration": "30:01",
    "god": "shani",
    "artist": "Hemant Chauhan"
  },
  {
    "title": "Navratri : Aarti Bhor Bhai Din Chadh Gaya Meri Ambe",
    "vid_id": "TaFsgp6ifjQ",
    "duration": "5:03",
    "god": "durga",
    "artist": "Anuradha Paudwal"
  },
  {
    "title": "काम होगा वही जिसे Kaam Hoga Wahi Jise",
    "vid_id": "kpopyQ2iCz0",
    "duration": "6:55",
    "god": "hanuman",
    "artist": "Lakhbir Singh Lakkha"
  },
  {
    "title": "O Maa Tu Chhupi Hai Kahan,Jai Jwala Maa",
    "vid_id": "Sss-LU1E2-k",
    "duration": "4:44",
    "god": "durga",
    "artist": "Anuradha Paudwal"
  },
  {
    "title": "Tainu Na Kawan Te Das Hor Kinoo Kawan",
    "vid_id": "C6GGt0EG4-E",
    "duration": "7:51",
    "god": "durga",
    "artist": "Narendra Chanchal"
  },
  {
    "title": "Ambe Bhawani - Maa Ki Chitthi Aayee",
    "vid_id": "u5R0uiqg4Pk",
    "duration": "6:05",
    "god": "durga",
    "artist": "Lakhbir Singh Lakkha"
  },
  {
    "title": "Nindre Pare Pare Chali Jaayan",
    "vid_id": "eUyG5rWvSqg",
    "duration": "7:57",
    "god": "ram",
    "artist": "Karnail Rana"
  },
  {
    "vid_id": "bkRCrEarkH8",
    "title": "Radha Rani Hamen Bhi Baata De Zara | राधा रानी हमें भी बता दे",
    "duration": "6:58",
    "god": "radha",
    "artist": "Charanjeet Singh Sondhi"
  },
  {
    "vid_id": "vcLFIRJ8Kd4",
    "title": "रावण रचित शिव तांडव स्त्रोत | Shiv Tandav Stotram",
    "duration": "8:06",
    "god": "shiv",
    "artist": "Pujya Bhaishre Rameshbhai Oza"
  },
  {
    "vid_id": "6D1FdZczNXI",
    "title": "Lingaashtakam | लिंगाष्टकम",
    "duration": "6:01",
    "god": "shiv",
    "artist": "Pujya Bhaishree Rameshbhai Oza"
  },
  {
    "vid_id": "EHkncEspk6Q",
    "title": "रामा रामा रटते रटते बीती रे उमरिया | Rama Rama Ratte Ratte",
    "duration": "3:47",
    "god": "ram",
    "artist": "Samarpit The Band"
  },
  {
    "vid_id": "MUFrk668K60",
    "title": "Enakkum Idam Undu | Murugan Songs",
    "duration": "5:17",
    "lang": "Tamil",
    "god": "murugan",
    "artist": "T. M. Soundararajan"
  },
  {
    "vid_id": "RFgomiaQLj0",
    "title": "Hey Ram Hey Ram | हे राम हे राम | राम भजन ",
    "duration": "4:22",
    "god": "ram",
    "artist": "Jagjit Singh"
  },
  {
    "vid_id": "dR3kI_iUqrU",
    "title": "Pallikattu Sabarimalaikku | Ayyappan Songs",
    "duration": "6:49",
    "lang": "Tamil",
    "god": "Ayyappan",
    "artist": "K. Veeramani"
  },
  {
    "vid_id": "6_OmPB8h2vU",
    "title": "Durga Hai Meri Maa| दुर्गा है मेरी माँ ",
    "duration": "4:21",
    "god": "durga",
    "artist": "Mahendra Kapoor"
  },
  {
    "vid_id": "NM9pHX6dqDc",
    "title": "Shyam Teri Bansi Pukare | श्याम तेरी बंसी पुकारे ",
    "duration": "6:36",
    "god": "krishna",
    "artist": "Ravindra Jain"
  },
  {
    "vid_id": "25vcZiT5LeY",
    "title": "Anup Jalota | Shyam Teri Bansi",
    "duration": "6:30",
    "god": "krishna",
    "artist": "Anup Jalota"
  },
  {
    "vid_id": "R_Jxg_MA8zo",
    "title": "नवरात्री पूजा की विधि | How To Perform Navratri Puja",
    "duration": "8:52",
    "god": "durga",
    "artist": "Aishwarya"
  },
  {
    "vid_id": "Hbb2Ymgzq4Y",
    "title": "Vishnu sahasranama | 1000 names of Vishnu | विष्णुसहस्रनाम | विष्नु के 1000 नाम ",
    "duration": "29:57",
    "god": "vishnu",
    "artist": "Saregama"
  },
  {
    "vid_id": "93Wu2Cg5FWc",
    "title": "Azhagellam Murugane | Murugan Songs",
    "duration": "3:34",
    "lang": "Tamil",
    "god": "murugan",
    "artist": "Sulamangalam Sisters"
  },
  {
    "vid_id": "xNv5qn7o0mE",
    "title": "Bholenath Ji ।  Official Music Video | Hansraj Raghuwanshi",
    "duration": "3:26",
    "god": "shiv",
    "artist": "Hansraj Raghuwanshi"
  },
  {
    "vid_id": "Yq22EQh6cmo",
    "title": "Suno Krishna Pyaare | सुनो कृष्ण प्यारे ",
    "duration": "6:30",
    "god": "krishna",
    "artist": "Swati Mishra"
  },
  {
    "vid_id": "dXn4PIaYdnM",
    "title": "गंगा मैया में जब तक | Ganga Maiya Men Jab Tak | गंगा की आरती",
    "duration": "6:10",
    "god": "devi",
    "artist": "Lata Mangeshkar"
  },
  {
    "vid_id": "3QfNBqyT43M",
    "title": "Unnaithan Pada Vandhen | Tamil Devotional Song",
    "duration": "3:49",
    "lang": "Tamil",
    "god": "murugan",
    "artist": "Sulamangalam Sisters"
  },
  {
    "vid_id": "0f8VCQ14_Lk",
    "title": "Annadhana Prabhuve | Ayyappan Song",
    "duration": "3:34",
    "god": "Ayyappan",
    "artist": "K. Veeramani"
  },
  {
    "vid_id": "swsJ4uoUpl0",
    "title": "Tum Dhondho Mujhe Gopal | Jagjit Singh",
    "duration": "7:30",
    "god": "krishna",
    "artist": "Jagjit Singh"
  },
  {
    "vid_id": "lKvIrEquKTI",
    "title": "Shivashtakam| शिवाष्टक स्तोत्रं | Mahadev Mantra | Powerful Shiv Mantra",
    "duration": "9:04",
    "god": "shiv",
    "artist": "Saregama"
  },
  {
    "vid_id": "3IpptvFQiqU",
    "title": "Bam Bam Bhole | Abhilipsa Panda",
    "duration": "3:13",
    "lang": "Tamil",
    "god": "shiv",
    "artist": "Abhilipsa Panda"
  },
  {
    "vid_id": "PycZjQT5_5M",
    "title": "Karpanai Endralum | Murugan Songs",
    "duration": "3:28",
    "lang": "Tamil",
    "god": "murugan",
    "artist": "T. M. Soundararajan"
  },
  {
    "vid_id": "dV5Y3xeLtf0",
    "title": "सारे दिन गुनगुनाएँगे श्रीकृष्ण का ये सूंदर धुन | कान्हा आन पड़ी मैं तेरे द्वार | कृष्णा भजन",
    "duration": "5:19",
    "god": "krishna",
    "artist": "Saregama"
  },
  {
    "vid_id": "pjOqj6R9AjY",
    "title": "श्री हनुमान चालीसा |Hanuman Chalisa",
    "duration": "5:54",
    "god": "hanuman",
    "artist": "Pragya Medha"
  },
  {
    "vid_id": "71cMcLFmUfg",
    "title": "Shiv Kailasho Ke Wasi | शिव कैलाशो के वासी ",
    "duration": "4:33",
    "god": "shiv",
    "artist": "Siddharth Mohan"
  },
  {
    "vid_id": "u30HcAQsgrU",
    "title": "Engey Manakkuthu | Ayyappan Songs",
    "duration": "5:44",
    "lang": "Tamil",
    "god": "Ayyappan",
    "artist": "K. Veeramani"
  },
  {
    "vid_id": "FKz8QCPhSY8",
    "title": "Dhol Baje Maa | Jidhar Dekho Jagrate",
    "duration": "7:24",
    "god": "durga",
    "artist": "Lakhbir Singh Lakha"
  },
  {
    "vid_id": "0oYY0LulS4w",
    "title": "हे राम स्वीकारो मेरे प्रणाम | Ram Sweekaro Mere Pranaam",
    "duration": "4:38",
    "god": "ram",
    "artist": "Saregama"
  },
  {
    "vid_id": "BDHyTGnQg3Q",
    "title": "श्याम तेरी बंसी  | Shyam Teri bansi",
    "duration": "6:44",
    "god": "krishna",
    "artist": "Saregama"
  },
  {
    "vid_id": "NveQcC_b9Qw",
    "title": "Tum Dhondho Mujhe Gopal | तुम ढूंढो मुझे गोपाल | Krishna Bhajan",
    "duration": "7:32",
    "god": "krishna",
    "artist": "Jagjit Singh"
  },
  {
    "vid_id": "1aNFTAMBhqU",
    "title": "Panniru Vizhigalile | Murugan Songs",
    "duration": "3:38",
    "lang": "Tamil",
    "god": "murugan",
    "artist": "Seerkazhi S. Govindarajan"
  },
  {
    "vid_id": "NeuKoZGrXKY",
    "title": "मारने वाला है भगवान , बचाने वाला है भगवान | Hari Darshan",
    "duration": "6:05",
    "god": "vishnu",
    "artist": "Lata Mangeshkar"
  },
  {
    "vid_id": "YS2ZvhPTVyg",
    "title": "Kothaiyin Thiruppavai| Krishnan Songs",
    "duration": "5:37",
    "lang": "Tamil",
    "god": "krishna",
    "artist": "K. Veeramani"
  },
  {
    "vid_id": "BuD-fxDNWKg",
    "title": "Devi Geet | Chalo Bulawa Aaya Hai | चलो बुलावा आया है | Ajay Bedi",
    "duration": "3:48",
    "god": "durga",
    "artist": "Ajay Bedi"
  },
  {
    "vid_id": "mL3hyQk-h1s",
    "title": "Tera Ram Ji Karenga Beda Paar |तेरा राम जी करेंगे बेडा पार ",
    "duration": "5:23",
    "god": "ram",
    "artist": "Hari Om Sharan"
  },
  {
    "vid_id": "73avMuj-vbE",
    "title": "आपके सर पर से काल को हर लेगा | माँ काली स्तोत्र ",
    "duration": "5:34",
    "god": "kali",
    "artist": "Saregama"
  },
  {
    "vid_id": "_Deqvr6td6s",
    "title": "Muruganai Kooppittu | Murugan Songs",
    "duration": "3:42",
    "lang": "Tamil",
    "god": "murugan",
    "artist": "T. M. Soundararajan"
  },
  {
    "vid_id": "xyfgTYBUy44",
    "title": "गोविंदा आन बसो |  Govinda Aan Baso",
    "duration": "4:21",
    "god": "krishna",
    "artist": "Maanya Arora"
  },
  {
    "vid_id": "G8WaambMT28",
    "title": "Varde Varde Varde | Jagjit Singh",
    "duration": "5:50",
    "god": "durga",
    "artist": "Jagjit Singh"
  },
  {
    "vid_id": "KTjMvz7PuA0",
    "title": "Ambe Charan Kamal Hain Tere | Jagjit Singh | Mata Bhajan",
    "duration": "6:03",
    "god": "durga",
    "artist": "Jagjit Singh"
  },
  {
    "vid_id": "CQ9izVC6lcs",
    "title": "Neeyallal Deivamillai | Murugan Songs",
    "duration": "3:54",
    "lang": "Tamil",
    "god": "murugan",
    "artist": "Seerkazhi S. Govindarajan"
  },
  {
    "vid_id": "8b6Pza35L1c",
    "title": "राम जी के नाम ने तो पाथर भी तारे | Ramji Ke Naam Ne To",
    "duration": "4:48",
    "god": "ram",
    "artist": "Hari Om Sharan"
  },
  {
    "vid_id": "3nATsNWJbmA",
    "title": "कर्पूर गौरव करुणावतारम | Karpoor Gauram Karunavataram",
    "duration": "6:07",
    "god": "shiv",
    "artist": "Saregama"
  },
  {
    "vid_id": "xxfte0uRcVI",
    "title": "ज्योती कलश चलके | Jyoti Kalash Chhalke | Lata Mangeshkar",
    "duration": "4:36",
    "god": "durga",
    "artist": "Lata Mangeshkar"
  },
  {
    "vid_id": "_G7vcT6a2CM",
    "title": "Sukh Karta Dukh Harta Gajanan | सुखकर्ता दु:खहर्ता गजानन ",
    "duration": "3:57",
    "lang": "Marathi",
    "god": "ganesh",
    "artist": "Ankit Sarang"
  },
  {
    "vid_id": "QHHs3RHwmaw",
    "title": "Mere Man Ke Andh Tamas Mein | मेरे मन के अंध तमस में ",
    "duration": "6:58",
    "god": "durga",
    "artist": "Jagjit Singh"
  },
  {
    "vid_id": "vz8CY5rOCbI",
    "title": "मैं तोह आरती उतारू रे | Main To Aarti Utaroon Re",
    "duration": "6:51",
    "god": "durga",
    "artist": "Usha Mangeshkar"
  },
  {
    "vid_id": "FLx7eevCdlQ",
    "title": "गोविंद बोलो हरी गोपाल बोलो ",
    "duration": "5:48",
    "god": "krishna",
    "artist": "Pragya Medha"
  },
  {
    "vid_id": "kTHm53B6yQA",
    "title": "Karpagavalli Nin Porpathangal| Amman Songs",
    "duration": "7:01",
    "lang": "Tamil",
    "god": "Amman",
    "artist": "T. M. Soundararajan"
  },
  {
    "vid_id": "3lTUrHetS6M",
    "title": "हे मनवा रे | He Manwa Re| हनुमान भक्ति गीत",
    "duration": "4:19",
    "god": "hanuman",
    "artist": "Mahendra Kapoor"
  },
  {
    "vid_id": "JzJjGntX1P0",
    "title": "हे राम हे राम | Hey Ram Hey Ram",
    "duration": "4:15",
    "god": "ram",
    "artist": "Jagjit Singh"
  },
  {
    "title": "Aigiri Nandini | महिषासुर मर्दिनी स्तोत्र",
    "vid_id": "442ewPgXHQ0",
    "duration": "15:14",
    "god": "durga",
    "artist": "Rajalakshmee Sanjay"
  },
  {
    "title": "Aditya Hrudayam Stotram | आदित्य हृदयम",
    "vid_id": "afdT_tkHWOE",
    "duration": "9:33",
    "god": "surya",
    "artist": "Rajshri Soul"
  },
  {
    "title": "Om Jai Lakshmi Mata Aarti| लक्ष्मी माता आरती ",
    "vid_id": "0D3VbBoJBrM",
    "duration": "4:52",
    "god": "laxmi",
    "artist": "Rajshri Soul"
  },
  {
    "title": "Ganpati Stotram | Mantra For Calmness",
    "vid_id": "8r7AWFkjVpw",
    "duration": "3:35",
    "god": "ganesh",
    "artist": "Rajshri Soul"
  },
  {
    "title": "Jai Adhyashakti | जय आद्यशक्ति",
    "vid_id": "JiTpnD20Elk",
    "duration": "12:21",
    "god": "durga",
    "artist": "Sanjeevani Bhelande"
  },
  {
    "title": "Aarti Saibaba | साईबाबा आरती ",
    "vid_id": "DT5PaaxItzY",
    "duration": "3:13",
    "god": "sai",
    "artist": "Rajshri Soul"
  },
  {
    "title": "Sukhkarta Dukhharta - Ganpati Aarti",
    "vid_id": "gFr5p5AyuD0",
    "duration": "2:00",
    "lang": "Marathi",
    "god": "ganesh",
    "artist": "Rajshri Soul"
  },
  {
    "title": "Om Jai Jagdish Hare Aarti| ॐ जय जगदीश हरे ",
    "vid_id": "012oY38Blvg",
    "duration": "4:51",
    "god": "vishnu",
    "artist": "Sanjeevani Bhelande"
  },
  {
    "title": "या कुंदेन्दु | Ya Kundendu Tusharahara Dhavala | Mantra For Knowledge",
    "vid_id": "DySzqHwNCxU",
    "duration": "2:29",
    "god": "saraswati",
    "artist": "Rajshri Soul"
  },
  {
    "title": "Durge Durghat Bhari Ma Durga Aarti",
    "vid_id": "OJKuNYsPMVU",
    "duration": "2:25",
    "lang": "Marathi",
    "god": "durga",
    "artist": "Sanjeevani Bhelande"
  },
  {
    "title": "Guru Brahma Guru Vishnu | Devotional Mantra For Clarity",
    "vid_id": "25YCfRo2b3E",
    "duration": "1:22",
    "god": "Guru",
    "artist": "Rajshri Soul"
  },
  {
    "title": "Full Navgraha Mantra | नवग्रह स्तोत्र / नवग्रह मंत्र",
    "vid_id": "g6zHBogmPnA",
    "duration": "3:43",
    "god": "navgraha",
    "artist": "Rajshri Soul"
  },
  {
    "title": "Jai Ganesh Deva Aarti | Ganpati Aarti",
    "vid_id": "IJKafzL8kLQ",
    "duration": "2:38",
    "god": "ganesh",
    "artist": "Rajshri Soul"
  },
  {
    "title": "Maha Ganapatim Manasa Smarami",
    "vid_id": "KO7xOHCnE4U",
    "duration": "4:35",
    "god": "ganesh",
    "artist": "Rajshri Soul"
  },
  {
    "title": "Full Mahalakshmi Ashtakam | महालक्ष्मी अष्टकम | Powerful Lakshmi Mantra For Wealth",
    "vid_id": "FrUa0ovoZJQ",
    "duration": "3:33",
    "god": "laxmi",
    "artist": "Rajshri Soul"
  },
  {
    "title": "Mahalakshmi Aarti",
    "vid_id": "Fu2x5HLOrCM",
    "duration": "2:44",
    "lang": "Marathi",
    "god": "laxmi",
    "artist": "Sanjeevani Bhelande"
  },
  {
    "title": "Yei O Vitthale Maze Mauli Ye | Vitthal Aarti",
    "vid_id": "8O7FU5KD5bE",
    "duration": "3:15",
    "lang": "Marathi",
    "god": "Vitthal",
    "artist": "Rajshri Soul"
  },
  {
    "title": "Sukhkarta Dukhharta | Shendur Lal Chadhayo | Shankar Aarti | Durge Durgat Bhari | Ghalin Lotangan",
    "vid_id": "Wk1ai8pEBQ4",
    "duration": "9:18",
    "lang": "Marathi",
    "god": "ganesh",
    "artist": "Rajshri Soul"
  },
  {
    "title": "Om Namah Shivaya 108 Times | Peaceful Shiva Mantra | ॐ नमः शिवाय ",
    "vid_id": "xBr9FxZQPjM",
    "duration": "11:56",
    "god": "shiv",
    "artist": "Rajshri Soul"
  },
  {
    "title": "Ram Raksha Stotra | श्रीरामरक्षास्तोत्र",
    "vid_id": "y2rPvroMk-8",
    "duration": "10:23",
    "god": "ram",
    "artist": "Rajshri Soul"
  },
  {
    "title": "Full Sri Suktam | श्री सूक्तम |Lakshmi Mantra For Wealth",
    "vid_id": "ThznwYxJ8po",
    "duration": "5:22",
    "god": "laxmi",
    "artist": "Rajshri Soul"
  },
  {
    "title": "Ghalin Lotangan Vandin Charan | Ganesh Aarti",
    "vid_id": "od-OOQ9OqyI",
    "duration": "1:33",
    "lang": "Marathi",
    "god": "ganesh",
    "artist": "Rajshri Soul"
  },
  {
    "title": "Jai Santoshi Mata Aarti | जय संतोषी माता आरती",
    "vid_id": "2DTf5rXaOJ0",
    "duration": "4:58",
    "god": "Santoshi Mata",
    "artist": "Sanjeevani Bhelande"
  },
  {
    "title": "Mahamrityunjaya Mantra 11 Times | Om Tryambakam Yajamahe",
    "vid_id": "gdKm1fZzMgI",
    "duration": "3:02",
    "god": "shiv",
    "artist": "Rajshri Soul"
  },
  {
    "title": "Jai Tulsi Mata - Tulsi Aarti",
    "vid_id": "4yVdfundS_o",
    "duration": "3:32",
    "god": "Tulsi",
    "artist": "Sanjeevani Bhelande"
  },
  {
    "title": "Jai Parvati Mata - Parvati Aarti",
    "vid_id": "0qr7TGcVjfQ",
    "duration": "5:12",
    "god": "parvati",
    "artist": "Sanjeevani Bhelande"
  },
  {
    "title": "Annapoorna Stotram | Devotional Chant | Rajalakshmee Sanjay",
    "vid_id": "DXVI5xKbdZQ",
    "duration": "12:31",
    "god": "Annapoorna",
    "artist": "Rajalakshmee Sanjay"
  },
  {
    "title": "Shanti Mantra| Om Saha Navavatu ",
    "vid_id": "gAy1vqRceo0",
    "duration": "12:28",
    "god": "prathna",
    "artist": "Sanjeevani Bhelande"
  },
  {
    "title": "Sri Devi Khadgamala Stotram | देवी खड्गमाला स्तोत्रम ",
    "vid_id": "EXrGP6YNFss",
    "duration": "6:10",
    "god": "devi",
    "artist": "Rajshri Soul"
  },
  {
    "title": "Om Shri Hanumate Namah | Hanuman Mantra 108 Times | Popular Hanuman Mantra For Peace",
    "vid_id": "VBM9c292C7A",
    "duration": "15:00",
    "god": "hanuman",
    "artist": "Rajshri Soul"
  },
  {
    "title": "Jamo Jamadu - Mataji No Thal ",
    "vid_id": "pHPg9dcvesc",
    "duration": "4:44",
    "lang": "Gujarati",
    "god": "Mataji",
    "artist": "Sanjeevani Bhelande"
  },
  {
    "title": "Full Durga Suktam | दुर्गा सूक्तम ",
    "vid_id": "620Rx1RROxs",
    "duration": "3:27",
    "god": "durga",
    "artist": "Rajshri Soul"
  },
  {
    "title": "Aarti Kunj Bihari Ki | Krishna Aarti",
    "vid_id": "_O0etszYEas",
    "duration": "4:01",
    "god": "krishna",
    "artist": "Sanjeevani Bhelande"
  },
  {
    "title": "Jai Ambe Gauri - Durga Aarti",
    "vid_id": "NUd6HTjTM5U",
    "duration": "7:52",
    "god": "durga",
    "artist": "Sanjeevani Bhelande"
  },
  {
    "title": "शांत हो श्रीगुरुदत्ता | Shant Ho Shri Gurudatta Song",
    "vid_id": "OCNemNACbYY",
    "duration": "5:19",
    "lang": "Marathi",
    "god": "Guru",
    "artist": "Rajshri Soul"
  },
  {
    "title": "Full Bhagya Suktam | भाग्य सूक्तम | Vedic Chanting",
    "vid_id": "Hw2T1N5vlmc",
    "duration": "3:37",
    "god": "Guru",
    "artist": "Rajshri Soul"
  },
  {
    "title": "Aarasur Na Ambe Maa - Mataji No Thal - Sanjeevani Bhelande - Devotional Songs",
    "vid_id": "SsvrpWh0hZY",
    "duration": "6:38",
    "lang": "Gujarati",
    "god": "durga",
    "artist": "Sanjeevani Bhelande"
  },
  {
    "title": "Shani Dev Aarti | शनिदेव आरती ",
    "vid_id": "42fouuhg9Pw",
    "duration": "2:35",
    "god": "shani",
    "artist": "Rajshri Soul"
  },
  {
    "title": "Sri Lakshmi Kubera Mantra | लक्ष्मी कुबेर मंत्र",
    "vid_id": "BCVTDeXQ-xY",
    "duration": "8:01",
    "god": "laxmi",
    "artist": "Rajshri Soul"
  },
  {
    "title": "Achyutam Keshavam Krishna Damodaram",
    "vid_id": "btOdAtmJBbw",
    "duration": "4:46",
    "god": "krishna",
    "artist": "Rajshri Soul"
  },
  {
    "title": "Trigunatmak Trimurti Aarti | Lord Dattatreya Aarti",
    "vid_id": "Grt4TFx1E8M",
    "duration": "2:37",
    "lang": "Marathi",
    "god": "Datta",
    "artist": "Rajshri Soul"
  },
  {
    "title": "Mudakaratha Modakam | Ganesha Pancharatnam | Popular Devotional Songs ",
    "vid_id": "bgnEJM0C1Cg",
    "duration": "7:16",
    "god": "ganesh",
    "artist": "Rajshri Soul"
  },
  {
    "title": "Lavthavti Vikrala Shiva Aarti",
    "vid_id": "dcJv2RiUc0k",
    "duration": "2:47",
    "lang": "Marathi",
    "god": "shiv",
    "artist": "Sanjeevani Bhelande"
  },
  {
    "title": "Vaishnav Jan To - Bhajan And Meaning",
    "vid_id": "xipue67yfPQ",
    "duration": "5:18",
    "lang": "Gujarati",
    "god": "vishnu",
    "artist": "Rajshri Soul"
  },
  {
    "title": "Mantra Pushpanjali | Ganesh Chaturthi Mantra ",
    "vid_id": "vY_9mautsC8",
    "duration": "3:18",
    "god": "ganesh",
    "artist": "Rajshri Soul"
  },
  {
    "title": "नवरात्रि आरती | Popular Durga Aarti",
    "vid_id": "jmYeZcqnw84",
    "duration": "8:57",
    "god": "durga",
    "artist": "Rajshri Soul"
  },
  {
    "title": "Yuge Atthavis Vitthala Aarti | युगे अठ्ठावीस आरती | Sanjeevani Bhelande ",
    "vid_id": "rahKfNNp2FI",
    "duration": "3:24",
    "lang": "Marathi",
    "god": "Vitthal",
    "artist": "Sanjeevani Bhelande"
  },
  {
    "title": "Shantakaram Bhujagashayanam 11 Times | शान्ताकारं भुजगशयनं | Vishnu Mantra For Peace",
    "vid_id": "Im5TK-glA9M",
    "duration": "7:03",
    "god": "vishnu",
    "artist": "Rajshri Soul"
  },
  {
    "title": "Ya Devi Sarvabhuteshu | Mantra For Energy",
    "vid_id": "ZoxFCt_Y76I",
    "duration": "8:07",
    "god": "devi",
    "artist": "Sanjeevani Bhelande"
  },
  {
    "title": "Asato Ma Sadgamaya",
    "vid_id": "Vwyo62x9yC4",
    "duration": "6:23",
    "god": "prathna",
    "artist": "Rajshri Soul"
  },
  {
    "title": "Jai Shiv Omkara - Popular Shiva Aarti",
    "vid_id": "YXiiaucRfSo",
    "duration": "5:11",
    "god": "shiv",
    "artist": "Rajshri Soul"
  },
  {
    "title": "Full Narayana Suktam | नारायणा सूक्तम | Ancient Vedic Chants In Sanskrit",
    "vid_id": "vLP6gdiDbOU",
    "duration": "5:31",
    "god": "vishnu",
    "artist": "Rajshri Soul"
  },
  {
    "title": "Sai Baba Aarti | आरती साई बाबा ",
    "vid_id": "tySLqE-3acs",
    "duration": "4:37",
    "god": "sai",
    "artist": "Rajshri Soul"
  },
  {
    "title": "Jai Ganesh Jai Ganesh Deva | जय गणेश जय गणेश देवा ",
    "vid_id": "yPamd9UzEJo",
    "duration": "2:35",
    "god": "ganesh",
    "artist": "Rajshri Soul"
  },
  {
    "title": "Aarti Tukaram | Sant Tukaram Aarti",
    "vid_id": "bYFZoFfW9so",
    "duration": "2:08",
    "lang": "Marathi",
    "god": "Sant Tukaram",
    "artist": "Rajshri Soul"
  },
  {
    "title": "Jai Jai Ram Krishna Hari 108 Times | Vitthal Maha Mantra",
    "vid_id": "wVWJOqMml4c",
    "duration": "6:29",
    "lang": "Marathi",
    "god": "Vitthal",
    "artist": "Rajshri Soul"
  },
  {
    "title": "Shendur Lal Chadhayo | Ganesh Aarti | शेंदुर लाल चढ़ायो | Ganpati Devotional Song ",
    "vid_id": "etcU9lexTFY",
    "duration": "2:04",
    "lang": "Marathi",
    "god": "ganesh",
    "artist": "Rajshri Soul"
  },
  {
    "title": "Guru Brahma Guru Vishnu | गुरु पूर्णिमा",
    "vid_id": "0W3QqjQSSNU",
    "duration": "3:00",
    "god": "Guru",
    "artist": "Rajshri Soul"
  },
  {
    "title": "Pradnya Vivardhan Stotra | प्रज्ञाविवर्धन स्तोत्रम् | Kartikeya Mantra",
    "vid_id": "6i7HuYjjthU",
    "duration": "2:52",
    "god": "Kartikeya",
    "artist": "Rajshri Soul"
  },
  {
    "title": "Vakratunda Mahakaya 108 Times | Powerful Ganesh Mantra For Success",
    "vid_id": "2Jt1HQe67jU",
    "duration": "2:55",
    "god": "ganesh",
    "artist": "Rajshri Soul"
  },
  {
    "title": "Vathapi Ganapathim Bhaje | Popular Devotional Ganpati Song",
    "vid_id": "Cg08mhvkPW8",
    "duration": "6:08",
    "god": "ganesh",
    "artist": "Rajshri Soul"
  },
  {
    "title": "Om Jai Veene Vaali | Saraswati Aarti",
    "vid_id": "khnJPuV_NBs",
    "duration": "3:26",
    "god": "saraswati",
    "artist": "Sanjeevani Bhelande"
  },
  {
    "title": "Om Jai Jagdish Hare Video Song",
    "vid_id": "ke5_35OtnhE",
    "duration": "3:37",
    "god": "vishnu",
    "artist": "Palak Muchhal"
  },
  {
    "title": "Gajananam Bhutaganadi Sevitam |Sloka of Shree Ganesha | Mantra For Peace & Focus",
    "vid_id": "agqwzb3YzQ0",
    "duration": "3:22",
    "god": "ganesh",
    "artist": "Rajshri Soul"
  },
  {
    "title": "Full Ram Aarti | राम आरती ",
    "vid_id": "71a5wGc9Q70",
    "duration": "2:57",
    "lang": "Marathi",
    "god": "ram",
    "artist": "Rajshri Soul"
  },
  {
    "title": "Hanuman Aarti Marathi | Satrane Uddane Aarti | हनुमान आरती",
    "vid_id": "Bfk6nx8Rg2Y",
    "duration": "1:54",
    "lang": "Marathi",
    "god": "hanuman",
    "artist": "Rajshri Soul"
  },
  {
    "title": "Gayatri Mantra With Meaning | गायत्री मंत्र 11 Times | Peaceful Chants",
    "vid_id": "ndZ-mBhkPrs",
    "duration": "3:21",
    "god": "prathna",
    "artist": "Rajshri Soul"
  },
  {
    "title": "Argala Stotram | Durga Saptashati | Navratri Special Song",
    "vid_id": "nK4mQqTZ7P4",
    "duration": "5:31",
    "god": "durga",
    "artist": "Rajshri Soul"
  },
  {
    "title": "Maruti Stotram Marathi | मारुती स्तोत्र",
    "vid_id": "4OdpjHbAkAk",
    "duration": "5:34",
    "lang": "Marathi",
    "god": "hanuman",
    "artist": "Rajshri Soul"
  },
  {
    "title": "Shiv Sahasranama Stotram | Powerful Lord Shiva Chant",
    "vid_id": "MiwjeaQZ1pY",
    "duration": "27:31",
    "god": "shiv",
    "artist": "Rajshri Soul"
  },
  {
    "title": "Navgraha Mantra | Mantra For All Nine Planets | Navgraha Stotram",
    "vid_id": "h8qTnwQRdhc",
    "duration": "11:10",
    "god": "navgraha",
    "artist": "Rajshri Soul"
  },
  {
    "title": "Vaishnav Jan To - Palak Muchhal",
    "vid_id": "ZawNypiSCOY",
    "duration": "3:15",
    "god": "vishnu",
    "artist": "Palak Muchhal"
  },
  {
    "title": "Venkatesh Aarti | Shree Balaji Aarti In Marathi",
    "vid_id": "JxC4y60Axvc",
    "duration": "1:26",
    "god": "hanuman",
    "artist": "Rajshri Soul"
  },
  {
    "title": "Guru Graha Mantra (4 lines) | Navgraha Mantra | Guru Graha Stotram ",
    "vid_id": "G8F5X7NjnQo",
    "duration": "3:19",
    "god": "navgraha",
    "artist": "Rajshri Soul"
  },
  {
    "title": "Karagre Vasate Lakshmi | कराग्रे वसते लक्ष्मी  Peaceful Early Morning Chants",
    "vid_id": "XJmt2eD_lbg",
    "duration": "3:08",
    "god": "laxmi",
    "artist": "Rajshri Soul"
  },
  {
    "title": "Ghalin Lotangan Vandeen Charan - Ganesh Chaturthi Songs",
    "vid_id": "iLLcyy82Is4",
    "duration": "1:54",
    "god": "ganesh",
    "artist": "Rajshri Soul"
  },
  {
    "title": "Shankar Aarti - Jai Shiv Omkara",
    "vid_id": "mb0IXEI0cPA",
    "duration": "5:10",
    "god": "shiv",
    "artist": "Sanjeevani Bhelande"
  },
  {
    "title": "Raghupati Raghav Raja Ram Full Video Song",
    "vid_id": "XybXCDs6UD0",
    "duration": "5:00",
    "god": "ram",
    "artist": "Palak Muchhal"
  },
  {
    "title": "Om Jai Jagdish Hare - Aarti - Sanjeevani Bhelande",
    "vid_id": "ZIFQAakYFq8",
    "duration": "4:54",
    "god": "vishnu",
    "artist": "Sanjeevani Bhelande"
  },
  {
    "title": "Aiso Hai Palna Krishna Lori | Krishna Devotional Song ",
    "vid_id": "HGiYkv2fh6o",
    "duration": "4:54",
    "god": "krishna",
    "artist": "Rajshri Soul"
  },
  {
    "title": "Jai Ganesh Jai Ganesh Deva | जय गणेश जय गणेश देवा | Ganesh Aarti | Ganpati Aarti",
    "vid_id": "yPamd9UzEJo",
    "duration": "2:35",
    "god": "ganesh",
    "artist": "Rajshri Soul"
  },
  {
    "title": "Pasaydan | पसायदान | Sant Dnyaneshwar",
    "vid_id": "s5_RyU4IOFY",
    "duration": "3:50",
    "lang": "Marathi",
    "god": "Sant Dnyaneshwar",
    "artist": "Rajshri Soul"
  },
  {
    "title": "Hanuman Gayatri Mantra | हनुमान गायत्री मंत्र",
    "vid_id": "Jp1lM2JO4aQ",
    "duration": "5:32",
    "god": "hanuman",
    "artist": "Rajshri Soul"
  },
  {
    "title": "Full Ganapathi Suktam | गणपति सूक्तम | Brahmanaspati Suktam | ब्रह्मणस्पति सूक्तम",
    "vid_id": "TR4XYoy-YQE",
    "duration": "3:08",
    "god": "ganesh",
    "artist": "Rajshri Soul"
  },
  {
    "title": "Om Narayanaya Vidmahe | Narayan Gayatri Mantra | Vishnu Gayatri Mantra ",
    "vid_id": "u2EX4wcpBX4",
    "duration": "3:49",
    "god": "vishnu",
    "artist": "Rajshri Soul"
  },
  {
    "title": "Sita Aarti | Sanjeevani Bhelande",
    "vid_id": "sgkXn-47gH8",
    "duration": "3:15",
    "god": "Sita",
    "artist": "Sanjeevani Bhelande"
  },
  {
    "title": "O Kanha Ab To Murli Ki - Krishna Bhajan | ओ कान्हा अब तो मुरली",
    "vid_id": "3YLog5mrAYM",
    "duration": "4:08",
    "god": "krishna",
    "artist": "Nova Spiritual"
  },
  {
    "title": "छोटी छोटी गैया छोटे छोटे ग्वाल Choti Choti Gaiya Chote Chote Gwal",
    "vid_id": "dD651ALK8PU",
    "duration": "6:36",
    "god": "krishna",
    "artist": "Nova Spiritual"
  },
  {
    "title": "Siya Ram Jay Ram Jay Jay Ram सिया राम जय राम जय जय राम ",
    "vid_id": "XDgeALlxDk4",
    "duration": "17:51",
    "god": "ram",
    "artist": "Nova Spiritual"
  },
  {
    "title": "Ghar Mein Padharo Gajanan Ji | घर में पधारो गजानंद जी मेरे घर में पधारो ",
    "vid_id": "nLUmRxc6140",
    "duration": "5:40",
    "god": "ganesh",
    "artist": "Nova Spiritual"
  },
  {
    "title": "Shendur Lal Chadhayo Achchha Gajmukhko - Ganesh Aarti",
    "vid_id": "bo62sjQ0CmE",
    "duration": "3:37",
    "lang": "Marathi",
    "god": "ganesh",
    "artist": "Nova Spiritual"
  },
  {
    "title": "Hey Gopal Krishna Karu Aarti Teri Full Song",
    "vid_id": "eNtCypenJPs",
    "duration": "4:09",
    "god": "krishna",
    "artist": "Nova Spiritual"
  },
  {
    "title": "Durga Kavach | श्री दुर्गा रक्षा कवच",
    "vid_id": "0rjuR_iiUMg",
    "duration": "17:30",
    "god": "durga",
    "artist": "Nova Spiritual"
  },
  {
    "title": "Durga Maa Aarti - Jai Ambe Gauri by Alka Yagnik",
    "vid_id": "Kw6J7e8lTDM",
    "duration": "8:08",
    "god": "durga",
    "Artist": "Alka Yagnik"
  },
  {
    "title": "Bhor Bhai Din Chad Gaya Meri Ambe",
    "vid_id": "NtVk69MSdIo",
    "duration": "6:33",
    "god": "durga",
    "Artist": "Alka Yagnik"
  },
  {
    "title": "Ek Baar To Radha Bankar Dekho Mere Sawariya",
    "vid_id": "_6Z7RzXdXrM",
    "duration": "8:59",
    "god": "krishna",
    "artist": "Nova Spiritual"
  },
  {
    "title": "पकड़ लो हाथ बनवारी Pakad Lo Hath Banvari",
    "vid_id": "lR3lY9fsIQQ",
    "duration": "7:09",
    "god": "krishna",
    "artist": "Nova Spiritual"
  },
  {
    "title": "श्री सूक्त ( ऋग्वेद) Sri Suktam ",
    "vid_id": "19S0Ip0rubo",
    "duration": "15:45",
    "god": "laxmi",
    "artist": "Nova Spiritual"
  },
  {
    "title": "Durga Ji Ki Aarti - Jai Ambe Gauri Full",
    "vid_id": "HAUxmNFkPfk",
    "duration": "8:08",
    "god": "durga",
    "artist": "Nova Spiritual"
  },
  {
    "title": "Saja Do Ghar Ko Gulshan Sa सजा दो घर को गुलशन सा ",
    "vid_id": "1_u-Koe8aog",
    "duration": "8:54",
    "god": "krishna",
    "artist": "Nova Spiritual"
  },
  {
    "title": "Vishnu Sahasranamam विष्णु सहस्रनाम ",
    "vid_id": "V4s0csapchI",
    "duration": "13:18",
    "god": "vishnu",
    "artist": "Nova Spiritual"
  },
  {
    "title": "Hari Sundar Nand Mukunda - हरि सुंदर नंद मुकुंदा",
    "vid_id": "z9e_lVCDPes",
    "duration": "7:26",
    "god": "krishna",
    "artist": "Nova Spiritual"
  },
  {
    "title": "Complete Vishwambhari Stuti | વિશ્વંભરી સ્તુતિ | Vishwambhari Stuti Gujarati | Vishwambhari Maa Song",
    "vid_id": "IU6k5cA9X94",
    "duration": "9:49",
    "lang": "Gujarati",
    "god": "durga",
    "artist": "Nova Spiritual"
  },
  {
    "title": "जरा इतना बता दे कान्हा Jara Itna Bata De Kanha",
    "vid_id": "MtydhrpiSug",
    "duration": "6:09",
    "god": "krishna",
    "artist": "Nova Spiritual"
  },
  {
    "title": "Rudrashtakam - Namami Shamishan Nirvan Roopam",
    "vid_id": "pytnhdLUXuU",
    "duration": "7:31",
    "god": "shiv",
    "artist": "Nova Spiritual"
  },
  {
    "title": "Krishna Mantra - Om Krishnaya Vasudevaya Haraye Paramatmane 108 Times",
    "vid_id": "OLWnCrUl6yA",
    "duration": "23:15",
    "god": "krishna",
    "artist": "Nova Spiritual"
  },
  {
    "title": "Raghupati Raghav Raja Ram | Beautiful Ram Bhajan",
    "vid_id": "0J8r01HsTe0",
    "duration": "8:09",
    "god": "ram",
    "artist": "Nova Spiritual"
  },
  {
    "title": "Lagan Tumse Laga Baithe Jo Hoga Dekha Jayega - Krishna Bhajan लगन तुमसे लगा बैठे",
    "vid_id": "Oix_uS2cWog",
    "duration": "5:58",
    "god": "krishna",
    "artist": "Nova Spiritual"
  },
  {
    "title": "हमारे साथ श्री रघुनाथ Hamare Sath Shri Raghunath | Ram Ji Ke Bhajan",
    "vid_id": "DgBqq6D07Gc",
    "duration": "7:10",
    "god": "ram",
    "artist": "Nova Spiritual"
  },
  {
    "title": "Shiv Panchakshar Stotra पंचाक्षर स्त्रोत | Nagendra Haraya Trilochanaya",
    "vid_id": "xFvfdjw2eno",
    "duration": "4:48",
    "god": "shiv",
    "artist": "Nova Spiritual"
  },
  {
    "title": "Ashutosh Shashank Shekhar | आशुतोष शशांक शेखर",
    "vid_id": "XZEWtYZH1iQ",
    "duration": "5:00",
    "god": "shiv",
    "Artist": "Ashutosh Shashank Shekhar"
  },
  {
    "title": "Ganpati Atharvashirsha गणपती अथर्वशीर्ष - Suresh Wadkar",
    "vid_id": "0jp74dSqSs0",
    "duration": "9:56",
    "lang": "Marathi",
    "god": "ganesh",
    "Artist": "Suresh Wadkar"
  },
  {
    "title": "ये चमक ये दमक Ye Chamak Ye Damak - Krishna Bhajan Sab Kuch Sarkar Tumhi Se Hai",
    "vid_id": "04x7qW_DS2Y",
    "duration": "5:58",
    "god": "krishna",
    "artist": "Nova Spiritual"
  },
  {
    "title": "Chaupai Sahib ਚੌਪਈ ਸਾਹਿਬ | Kirtan Roop",
    "vid_id": "MSqOFIDEQ5g",
    "duration": "7:27",
    "lang": "Punjabi",
    "god": "Gurbani",
    "Artist": "Arvinder Singh"
  },
  {
    "title": "किशोरी कुछ ऐसा इंतज़ाम हो जाये | Kishori Kuch Aisa Intjam Ho Jaye Full Song | Radha Rani Ke Bhajan",
    "vid_id": "kwFBard6t60",
    "duration": "11:18",
    "god": "radha",
    "artist": "Nova Spiritual"
  },
  {
    "title": "श्री बांके बिहारी तेरी आरती गाऊं Shri Banke Bihari Teri Aarti Gaun | Krishna Aarti | Krishna Bhajan",
    "vid_id": "6LO2PRgbutc",
    "duration": "6:48",
    "god": "krishna",
    "artist": "Nova Spiritual"
  },
  {
    "title": "रामचरितमानस Ramcharitmanas - Ramayan Siddh Chaupai | Bhakti Song | Ram Bhajan | Ram Charit Manas",
    "vid_id": "4D7qFBCOzRI",
    "duration": "18:54",
    "god": "ram",
    "artist": "Nova Spiritual"
  },
  {
    "title": "Krishna Aarti - Main Aarti Teri Gau O Keshav Kunj Bihari",
    "vid_id": "gIH5dvdnixU",
    "duration": "4:51",
    "god": "krishna",
    "artist": "Nova Spiritual"
  },
  {
    "title": "Shree Ram Chandra Kripalu Bhajman | कृपालु भजमन",
    "vid_id": "EiBdfBciDA0",
    "duration": "3:23",
    "god": "ram",
    "artist": "Nova Spiritual"
  },
  {
    "title": "फूलों में सज रहे हैं Phoolo Me Saj Rahe Hain",
    "vid_id": "e9n79r4J9HE",
    "duration": "8:17",
    "god": "krishna",
    "artist": "Nova Spiritual"
  },
  {
    "title": "Adharam Madhuram - Madhurashtakam",
    "vid_id": "sdZpM8paUnM",
    "duration": "5:34",
    "god": "krishna",
    "artist": "Nova Spiritual"
  },
  {
    "title": "Kanakadhara Stotram - Full Version Original | Lakshmi Stotram | Laxmi Devi Songs",
    "vid_id": "tOXnp1fogPY",
    "duration": "9:05",
    "god": "laxmi",
    "artist": "Nova Spiritual"
  },
  {
    "title": "हनुमान चालीसा Hanuman Chalisa",
    "vid_id": "i-ckCDjwnBs",
    "duration": "7:24",
    "god": "hanuman",
    "artist": "Nova Spiritual"
  },
  {
    "title": "Hey Sharde Maa हे शारदे मां ",
    "vid_id": "p_qjOEI1S1k",
    "duration": "5:24",
    "god": "saraswati",
    "artist": "Nova Spiritual"
  },
  {
    "title": "कालभैरवाष्टकम् स्तोत्र | Kalbhairavashtak",
    "vid_id": "_CQDgICh-dk",
    "duration": "4:58",
    "god": "shiv",
    "artist": "Nova Spiritual"
  },
  {
    "title": "मोहन आओ तो सरी Mohan Aao To Sahi",
    "vid_id": "Np1QzgIo5es",
    "duration": "6:43",
    "god": "krishna",
    "Artist": "Meera Bai"
  },
  {
    "title": "Annapurna Stotram - Annapurna Ashtakam",
    "vid_id": "ZRC1ngWNUUo",
    "duration": "7:52",
    "god": "parvati",
    "artist": "Nova Spiritual"
  },
  {
    "title": "Shri Ram Chandra Kripalu Bhajman ",
    "vid_id": "m58fAjQOJJ0",
    "duration": "6:05",
    "god": "ram",
    "artist": "Nova Spiritual"
  },
  {
    "title": "Jagajjalapalam Kachad Kanda Malam | Hari Stotram",
    "vid_id": "votvQKdxWzw",
    "duration": "7:43",
    "god": "krishna",
    "artist": "Nova Spiritual"
  },
  {
    "title": "ओ बरसाने वाली गुलाम तेरो बनवारी O Barsane Wali Gulam Tero Banwari",
    "vid_id": "bw8IeRM3wzA",
    "duration": "7:58",
    "god": "krishna",
    "artist": "Nova Spiritual"
  },
  {
    "title": "Namaste Narasimhaya नमस्ते नरसिंहाय ",
    "vid_id": "zAf6Q7Hk6dY",
    "duration": "5:57",
    "god": "vishnu",
    "artist": "Nova Spiritual"
  },
  {
    "title": "दारिद्र्य दुख दहन शिव स्तोत्र Daridraya Dukha Dahana Shiva Stotram",
    "vid_id": "KK9PRb2zf7A",
    "duration": "6:00",
    "god": "shiv",
    "artist": "Nova Spiritual"
  },
  {
    "title": "शिव चालीसा Shiv Chalisa Full with Lyrics",
    "vid_id": "5tiMiWRqpgg",
    "duration": "10:13",
    "god": "shiv",
    "Artist": "Lakhbir Singh Lakha"
  },
  {
    "title": "Mera Aapki Kripa Se Sab Kaam Ho Raha Hai",
    "vid_id": "I1oR3MNHAFk",
    "duration": "6:26",
    "god": "krishna",
    "artist": "Nova Spiritual"
  },
  {
    "title": "गर्भ चालीसा Garbh Chalisa with Lyrics | Garbh Sanskar",
    "vid_id": "F6hDYejEphw",
    "duration": "8:16",
    "god": "special, prathna",
    "artist": "Nova Spiritual"
  },
  {
    "title": "नगरी हो अयोध्या सी Nagri Ho Ayodhya Si",
    "vid_id": "by_Z8AofRnE",
    "duration": "6:57",
    "god": "ram",
    "artist": "Nova Spiritual"
  },
  {
    "title": "Choti Choti Gaiya Chote Chote Gwal",
    "vid_id": "Um-EjBs3cCs",
    "duration": "6:38",
    "god": "krishna",
    "artist": "Nova Spiritual"
  },
  {
    "title": "Sitaram Sitaram Sitaram Kahiye",
    "vid_id": "Gbkf3SS7ds8",
    "duration": "7:10",
    "god": "ram",
    "artist": "Nova Spiritual"
  },
  {
    "title": "श्री राधा चालीसा Shri Radha Chalisa",
    "vid_id": "nLydYdxcQag",
    "duration": "10:13",
    "god": "radha",
    "Artist": "Kumar Vishu"
  },
  {
    "title": "Durga Ji Ki Aarti - Jai Ambe Gauri | माता जी की आरती | दुर्गा आरती",
    "vid_id": "dp32mzyuWPk",
    "duration": "8:08",
    "god": "durga",
    "artist": "Nova Spiritual"
  },
  {
    "title": "Rama Rama Ratte Ratte Biti Re Umariya | रामा रामा रटते रटते बीती रे उमरिया",
    "vid_id": "hwBBy74_Z5w",
    "duration": "7:44",
    "god": "ram",
    "artist": "Nova Spiritual"
  },
  {
    "title": "Ghar Me Padharo Laxmi Maiya घर में पधारो लक्ष्मी मैया ",
    "vid_id": "H2r9M66CQPk",
    "duration": "6:10",
    "god": "laxmi",
    "artist": "Nova Spiritual"
  },
  {
    "title": "Krishnashtakam - Bhaje Vrajaika Mandanam",
    "vid_id": "PvdeDNeCiQc",
    "duration": "9:10",
    "god": "krishna",
    "artist": "Nova Spiritual"
  },
  {
    "title": "Mere Banke Bihari Lal Tu Itna Na Kariyo Singar | मेरे बांके बिहारी लाल",
    "vid_id": "PkAadWTuFxY",
    "duration": "4:51",
    "god": "krishna",
    "artist": "Nova Spiritual"
  },
  {
    "title": "आशुतोष शशांक शेखर | Ashutosh Shashank Shekhar",
    "vid_id": "flFRb1AYIQY",
    "duration": "5:01",
    "god": "shiv",
    "Artist": "Ashutosh Shashank Shekhar"
  },
  {
    "title": "Panchmukhi Hanuman Kavach| पंचमुखी हनुमान कवच",
    "vid_id": "3QKaQ4tGf7Y",
    "duration": "8:01",
    "god": "hanuman",
    "Artist": "Suresh Wadkar"
  },
  {
    "title": "जगत के रंग क्या देखूं Jagat Ke Rang Kya Dekhu - Krishna Bhajan | Bhakti Song | Tera Deedar Kafi Hai",
    "vid_id": "pEhNcjtv04Y",
    "duration": "7:30",
    "god": "krishna",
    "artist": "Nova Spiritual"
  },
  {
    "title": "अच्युतम केशवम Achyutham Keshavam",
    "vid_id": "DlxBVGLobMI",
    "duration": "7:04",
    "god": "krishna",
    "artist": "Nova Spiritual"
  },
  {
    "title": "Ashtalakshmi Stotram - Sacred Chant of MahaLakshmi",
    "vid_id": "mld5oIvM1b0",
    "duration": "6:59",
    "god": "laxmi",
    "artist": "Nova Spiritual"
  },
  {
    "title": "काली चालीसा Kali Chalisa with Lyrics",
    "vid_id": "Gd_fmyIMQeU",
    "duration": "9:48",
    "god": "kali",
    "artist": "Nova Spiritual"
  },
  {
    "title": "सजा दो घर को गुलशन सा Saja Do Ghar Ko Gulshan Sa",
    "vid_id": "_pqSGK7XwPI",
    "duration": "8:55",
    "god": "ganesh",
    "artist": "Nova Spiritual"
  },
  {
    "title": "श्री कृष्ण गोविन्द हरे मुरारी Shri Krishna Govind Hare Murari",
    "vid_id": "_jhiRnGSIqs",
    "duration": "6:24",
    "god": "krishna",
    "artist": "Nova Spiritual"
  },
  {
    "title": "Siddha Kunjika Stotram सिद्ध कुंजिका स्तोत्र ",
    "vid_id": "5wNSs8y7d3w",
    "duration": "5:11",
    "god": "durga",
    "artist": "Nova Spiritual"
  },
  {
    "title": "गायत्री चालीसा Gayatri Chalisa",
    "vid_id": "RMRAIZdZzwM",
    "duration": "8:06",
    "god": "gayatri",
    "artist": "Nova Spiritual"
  },
  {
    "title": "सजा दो घर को गुलशन सा अवध में राम आए है Awadh Me Ram Aaye Hai",
    "vid_id": "Ilde1DXgATE",
    "duration": "8:55",
    "god": "ram",
    "artist": "Nova Spiritual"
  },
  {
    "title": "Raghupati Raghav Raja Ram",
    "vid_id": "Gtfufkz68KM",
    "duration": "7:50",
    "god": "ram",
    "artist": "Nova Spiritual"
  },
  {
    "title": "Kanhaiya Teri Murat Badi Pyari Kage",
    "vid_id": "reX51MNfQTY",
    "duration": "7:10",
    "god": "krishna",
    "artist": "Nova Spiritual"
  },
  {
    "title": "ॐ मंगलम Om Mangalam",
    "vid_id": "oSXeTwb9Lb4",
    "duration": "13:27",
    "god": "shiv",
    "artist": "Nova Spiritual"
  },
  {
    "title": "भगवान जी का भोग लगाते समय इस भजन को जरूर गायें | Brij Ke Rasiya",
    "vid_id": "zjy59797SLA",
    "duration": "9:49",
    "god": "krishna",
    "artist": "Nova Spiritual"
  },
  {
    "title": "Nand Ke Anand Bhayo Jai Kanhaiya Lal Ki",
    "vid_id": "rSKgqcv-eoc",
    "duration": "10:25",
    "god": "krishna",
    "artist": "Nova Spiritual"
  },
  {
    "title": "हनुमान चालिसा Hanuman Chalisa Lofi",
    "vid_id": "aP70Do2XHww",
    "duration": "9:31",
    "god": "hanuman",
    "artist": "Nova Spiritual"
  },
  {
    "title": "अष्टलक्ष्मी स्तोत्र Ashtalakshmi Stotram Full - Sumanasa Vandita Sundari",
    "vid_id": "7Dtc0q0IsOM",
    "duration": "6:59",
    "god": "laxmi",
    "artist": "Nova Spiritual"
  },
  {
    "title": "दुर्गा चालीसा | Durga Chalisa Full",
    "vid_id": "x9a-3kJ1ioM",
    "duration": "9:51",
    "god": "durga",
    "Artist": "Anuradha Paudwal"
  },
  {
    "title": "दुर्गा चालीसा |Durga Chalisa Fast",
    "vid_id": "O8c39grZzNM",
    "duration": "4:58",
    "god": "durga",
    "Artist": "Anuradha Paudwal"
  },
  {
    "title": "जय गणेश जय जय गणेश देवा Jai Ganesh Jai Jai Ganesh Deva",
    "vid_id": "uD56KPJRwu0",
    "duration": "3:35",
    "god": "ganesh",
    "artist": "Nova Spiritual"
  },
  {
    "title": "Aashapura Maiya Ka Dwar",
    "vid_id": "kqhwixNhBn4",
    "duration": "6:32",
    "god": "durga",
    "Artist": "Asha Bhosle"
  },
  {
    "title": "Jitna Radha Roi Roi Kanha Ke Liye Song | जितना राधा रोई रोई कान्हा के लिए ",
    "vid_id": "Pkl7-jerfok",
    "duration": "7:59",
    "god": "radha",
    "artist": "Nova Spiritual"
  },
  {
    "title": "श्री सूक्त |Sri Suktam Path Fast",
    "vid_id": "OXSsyzxWqnY",
    "duration": "5:27",
    "god": "laxmi",
    "artist": "Nova Spiritual"
  },
  {
    "title": "Kitna Pyara Hai Singar कितना प्यारा है सिंगार ",
    "vid_id": "C7SBU5DlmKs",
    "duration": "7:54",
    "god": "krishna",
    "artist": "Nova Spiritual"
  },
  {
    "title": "गायत्री माता की आरती Gayatri Mata Ki Aarti",
    "vid_id": "-N8U1TQwdfs",
    "duration": "8:05",
    "god": "gayatri",
    "artist": "Nova Spiritual"
  },
  {
    "title": "कनकधारा स्तोत्र | Kanakadhara Stotram Fast",
    "vid_id": "jVuK3lpGj5U",
    "duration": "5:15",
    "god": "laxmi",
    "artist": "Nova Spiritual"
  },
  {
    "title": "Mera Aapki Kripa Se Sab Kaam Ho Raha Hai | करते हो तुम कन्हैया मेरा नाम हो रहा है",
    "vid_id": "DuItYpHV4G8",
    "duration": "6:47",
    "god": "krishna",
    "artist": "Nova Spiritual"
  },
  {
    "title": "तेरी मंद मंद मुस्कनिया पे बलिहार सांवरे Teri Mand Mand Muskaniya Pe",
    "vid_id": "6cf-qZok-2c",
    "duration": "6:08",
    "god": "krishna",
    "artist": "Nova Spiritual"
  },
  {
    "title": "मोहन से दिल क्यों लगाया हैं Mohan Se Dil Kyon Lagaya Hai",
    "vid_id": "pVFi-thv-sU",
    "duration": "7:52",
    "god": "krishna",
    "artist": "Nova Spiritual"
  },
  {
    "title": "शिव चालीसा | Shiv Chalisa Fast",
    "vid_id": "NdjYgS4Ewm8",
    "duration": "5:39",
    "god": "shiv",
    "Artist": "Anuradha Paudwal"
  },
  {
    "title": "Achyutam Keshavam Ram Narayanam | Vishnu Songs",
    "vid_id": "Ca5Mwri3vrs",
    "duration": "7:11",
    "god": "vishnu",
    "artist": "Nova Spiritual"
  },
  {
    "title": "Ram Raksha Stotra (श्रीरामरक्षास्तोत्र) Fast",
    "vid_id": "NYakpChmUb0",
    "duration": "6:24",
    "god": "ram",
    "artist": "Nova Spiritual"
  },
  {
    "title": "Ganesh Aarti - Jai Ganesh Jai Ganesh Deva | जय गणेश जय गणेश देवा",
    "vid_id": "hunXk6Lb2Ek",
    "duration": "3:19",
    "god": "ganesh",
    "Artist": "Alka Yagnik"
  },
  {
    "title": "लिंगाष्टकम स्तोत्र - Lingashtakam |Shiv Lingashtakam",
    "vid_id": "vlIR42OuP70",
    "duration": "4:17",
    "god": "shiv",
    "artist": "Nova Spiritual"
  },
  {
    "title": "तेरा किसने किया सिंगार सांवरे Tera Kisne Kiya Singar Sanware",
    "vid_id": "FY5qlGwT6JE",
    "duration": "8:18",
    "god": "krishna",
    "artist": "Nova Spiritual"
  },
  {
    "title": "Subah Savere Lekar Tera Naam Prabhu | Prarthana प्रार्थना | Bhajan | सुबह सवेरे लेकर तेरा नाम प्रभु",
    "vid_id": "QjeAs9Bsk3g",
    "duration": "5:32",
    "god": "special, prathna",
    "artist": "Nova Spiritual"
  },
  {
    "title": "Lakh Khushian Patshahian - Shabad Gurbani",
    "vid_id": "7cwEUXxhr-E",
    "duration": "14:32",
    "lang": "Punjabi",
    "god": "Gurbani",
    "Artist": "Arvinder Singh"
  }
]
